                        2852    BINARY_SUBSCR                   
                        2862    LOAD_FAST                       51: t4r1
                        2864    COMPARE_OP                      3 (!=)
                        2870    POP_JUMP_FORWARD_IF_FALSE       44 (to 2960)
                        2872    LOAD_CONST                      57: 'برای اعمال تغییراتی که در نوع سرویس انجام داده اید، نیاز است نرم افزار را بسته و دوباره اجرا نمایید'
                        2874    LOAD_FAST                       0: self
                        2876    LOAD_ATTR                       5: automation
                        2886    STORE_ATTR                      6: last_error
                        2896    LOAD_GLOBAL                     15: NULL + time
                        2908    LOAD_ATTR                       7: time
                        2918    PRECALL                         0
                        2922    CALL                            0
                        2932    LOAD_CONST                      58: 5
                        2934    BINARY_OP                       0 (+)
                        2938    LOAD_FAST                       0: self
                        2940    LOAD_ATTR                       5: automation
                        2950    STORE_ATTR                      8: last_error_time
                        2960    LOAD_FAST                       58: settings_dict
                        2962    LOAD_FAST                       0: self
                        2964    STORE_ATTR                      4: settings
                        2974    LOAD_FAST                       0: self
                        2976    LOAD_METHOD                     9: parseProxyList
                        2998    LOAD_FAST                       0: self
                        3000    LOAD_ATTR                       4: settings
                        3010    LOAD_CONST                      59: 't6e2'
                        3012    BINARY_SUBSCR                   
                        3022    PRECALL                         1
                        3026    CALL                            1
                        3036    POP_TOP                         
                        3038    LOAD_FAST                       0: self
                        3040    LOAD_METHOD                     10: saveSettings
                        3062    PRECALL                         0
                        3066    CALL                            0
                        3076    POP_TOP                         
                        3078    LOAD_CLOSURE                    62: enableChildren
                        3080    BUILD_TUPLE                     1
                        3082    LOAD_CONST                      60: <CODE> enableChildren
                        3084    MAKE_FUNCTION                   8
                        3086    STORE_DEREF                     62: enableChildren
                        3088    PUSH_NULL                       
                        3090    LOAD_DEREF                      62: enableChildren
                        3092    LOAD_FAST                       0: self
                        3094    PRECALL                         1
                        3098    CALL                            1
                        3108    POP_TOP                         
                        3110    LOAD_CONST                      4: False
                        3112    LOAD_FAST                       0: self
                        3114    STORE_ATTR                      11: is_show_setting_windos
                        3124    LOAD_GLOBAL                     24: jbdb_license
                        3136    POP_JUMP_FORWARD_IF_TRUE        140 (to 3418)
                        3138    LOAD_FAST                       0: self
                        3140    LOAD_ATTR                       13: auto_start_check
                        3150    LOAD_METHOD                     0: state
                        3172    LOAD_CONST                      61: '!alternate'
                        3174    LOAD_CONST                      62: 'disabled'
                        3176    BUILD_LIST                      2
                        3178    PRECALL                         1
                        3182    CALL                            1
                        3192    POP_TOP                         
                        3194    LOAD_FAST                       0: self
                        3196    LOAD_ATTR                       14: auto_start_check_along_all
                        3206    LOAD_METHOD                     0: state
                        3228    LOAD_CONST                      61: '!alternate'
                        3230    LOAD_CONST                      62: 'disabled'
                        3232    BUILD_LIST                      2
                        3234    PRECALL                         1
                        3238    CALL                            1
                        3248    POP_TOP                         
                        3250    LOAD_FAST                       0: self
                        3252    LOAD_ATTR                       15: temporary_proxy_changer_page_one
                        3262    LOAD_METHOD                     0: state
                        3284    LOAD_CONST                      61: '!alternate'
                        3286    LOAD_CONST                      62: 'disabled'
                        3288    BUILD_LIST                      2
                        3290    PRECALL                         1
                        3294    CALL                            1
                        3304    POP_TOP                         
                        3306    LOAD_FAST                       0: self
                        3308    LOAD_ATTR                       16: temporary_proxy_changer_page_two
                        3318    LOAD_METHOD                     0: state
                        3340    LOAD_CONST                      61: '!alternate'
                        3342    LOAD_CONST                      62: 'disabled'
                        3344    BUILD_LIST                      2
                        3346    PRECALL                         1
                        3350    CALL                            1
                        3360    POP_TOP                         
                        3362    LOAD_FAST                       0: self
                        3364    LOAD_ATTR                       17: temporary_entry_proxy_change_time
                        3374    LOAD_METHOD                     0: state
                        3396    LOAD_CONST                      62: 'disabled'
                        3398    BUILD_LIST                      1
                        3400    PRECALL                         1
                        3404    CALL                            1
                        3414    POP_TOP                         
                        3416    JUMP_FORWARD                    158 (to 3734)
                        3418    LOAD_FAST                       0: self
                        3420    LOAD_ATTR                       15: temporary_proxy_changer_page_one
                        3430    LOAD_METHOD                     0: state
                        3452    LOAD_FAST                       0: self
                        3454    LOAD_ATTR                       4: settings
                        3464    LOAD_CONST                      63: 't6c2'
                        3466    BINARY_SUBSCR                   
                        3476    POP_JUMP_FORWARD_IF_FALSE       4 (to 3486)
                        3478    LOAD_CONST                      61: '!alternate'
                        3480    LOAD_CONST                      2: 'selected'
                        3482    BUILD_LIST                      2
                        3484    JUMP_FORWARD                    2 (to 3490)
                        3486    LOAD_CONST                      61: '!alternate'
                        3488    BUILD_LIST                      1
                        3490    PRECALL                         1
                        3494    CALL                            1
                        3504    POP_TOP                         
                        3506    LOAD_FAST                       0: self
                        3508    LOAD_ATTR                       16: temporary_proxy_changer_page_two
                        3518    LOAD_METHOD                     0: state
                        3540    LOAD_FAST                       0: self
                        3542    LOAD_ATTR                       4: settings
                        3552    LOAD_CONST                      64: 't6c3'
                        3554    BINARY_SUBSCR                   
                        3564    POP_JUMP_FORWARD_IF_FALSE       4 (to 3574)
                        3566    LOAD_CONST                      61: '!alternate'
                        3568    LOAD_CONST                      2: 'selected'
                        3570    BUILD_LIST                      2
                        3572    JUMP_FORWARD                    2 (to 3578)
                        3574    LOAD_CONST                      61: '!alternate'
                        3576    BUILD_LIST                      1
                        3578    PRECALL                         1
                        3582    CALL                            1
                        3592    POP_TOP                         
                        3594    LOAD_FAST                       0: self
                        3596    LOAD_ATTR                       17: temporary_entry_proxy_change_time
                        3606    LOAD_METHOD                     18: delete
                        3628    LOAD_CONST                      65: 0
                        3630    LOAD_GLOBAL                     6: END
                        3642    PRECALL                         2
                        3646    CALL                            2
                        3656    POP_TOP                         
                        3658    LOAD_FAST                       0: self
                        3660    LOAD_ATTR                       17: temporary_entry_proxy_change_time
                        3670    LOAD_METHOD                     19: insert
                        3692    LOAD_CONST                      65: 0
                        3694    LOAD_FAST                       0: self
                        3696    LOAD_ATTR                       4: settings
                        3706    LOAD_CONST                      54: 't6e1'
                        3708    BINARY_SUBSCR                   
                        3718    PRECALL                         2
                        3722    CALL                            2
                        3732    POP_TOP                         
                        3734    LOAD_GLOBAL                     41: NULL + zip
                        3746    LOAD_FAST                       0: self
                        3748    LOAD_ATTR                       21: check_buttons_list
                        3758    LOAD_FAST                       0: self
                        3760    LOAD_ATTR                       22: check_buttons_state_list
                        3770    PRECALL                         2
                        3774    CALL                            2
                        3784    GET_ITER                        
                        3786    FOR_ITER                        45 (to 3878)
                        3788    UNPACK_SEQUENCE                 2
                        3792    STORE_FAST                      59: i
                        3794    STORE_FAST                      60: j
                        3796    LOAD_CONST                      61: '!alternate'
                        3798    BUILD_LIST                      1
                        3800    LOAD_GLOBAL                     47: NULL + list
                        3812    LOAD_FAST                       60: j
                        3814    PRECALL                         1
                        3818    CALL                            1
                        3828    BINARY_OP                       0 (+)
                        3832    STORE_FAST                      61: x
                        3834    LOAD_FAST                       59: i
                        3836    LOAD_METHOD                     0: state
                        3858    LOAD_FAST                       61: x
                        3860    PRECALL                         1
                        3864    CALL                            1
                        3874    POP_TOP                         
                        3876    JUMP_BACKWARD                   46 (to 3786)
                        3878    LOAD_GLOBAL                     48: os
                        3890    LOAD_ATTR                       25: path
                        3900    LOAD_METHOD                     26: exists
                        3922    LOAD_CONST                      66: 'JCS.exe'
                        3924    PRECALL                         1
                        3928    CALL                            1
                        3938    POP_JUMP_FORWARD_IF_TRUE        29 (to 3998)
                        3940    LOAD_FAST                       0: self
                        3942    LOAD_ATTR                       4: settings
                        3952    LOAD_CONST                      34: 't2c3'
                        3954    BINARY_SUBSCR                   
                        3964    POP_JUMP_FORWARD_IF_FALSE       16 (to 3998)
                        3966    LOAD_GLOBAL                     55: NULL + showDownloadJCS
                        3978    LOAD_CONST                      67: 'نرم افزار سرویس حل کپچا نصب نشده است. با استفاده از دکمه زیر این سرویس را نصب کنید'
                        3980    LOAD_FAST                       0: self
                        3982    PRECALL                         2
                        3986    CALL                            2
                        3996    POP_TOP                         
                        3998    LOAD_FAST                       0: self
                        4000    LOAD_ATTR                       4: settings
                        4010    LOAD_CONST                      34: 't2c3'
                        4012    BINARY_SUBSCR                   
                        4022    POP_JUMP_FORWARD_IF_FALSE       27 (to 4078)
                        4024    LOAD_GLOBAL                     57: NULL + startJCS
                        4036    PRECALL                         0
                        4040    CALL                            0
                        4050    POP_TOP                         
                        4052    LOAD_CONST                      3: True
                        4054    LOAD_FAST                       0: self
                        4056    LOAD_ATTR                       5: automation
                        4066    STORE_ATTR                      29: use_local_uc
                        4076    JUMP_FORWARD                    67 (to 4212)
                        4078    LOAD_CONST                      4: False
                        4080    LOAD_FAST                       0: self
                        4082    LOAD_ATTR                       5: automation
                        4092    STORE_ATTR                      29: use_local_uc
                        4102    LOAD_GLOBAL                     60: jcs_handle
                        4114    POP_JUMP_FORWARD_IF_NONE        48 (to 4212)
                        4116    LOAD_GLOBAL                     63: NULL + subprocess
                        4128    LOAD_ATTR                       32: call
                        4138    LOAD_CONST                      68: 'taskkill'
                        4140    LOAD_CONST                      69: '/F'
                        4142    LOAD_CONST                      70: '/T'
                        4144    LOAD_CONST                      71: '/PID'
                        4146    LOAD_GLOBAL                     67: NULL + str
                        4158    LOAD_GLOBAL                     60: jcs_handle
                        4170    LOAD_ATTR                       34: pid
                        4180    PRECALL                         1
                        4184    CALL                            1
                        4194    BUILD_LIST                      5
                        4196    PRECALL                         1
                        4200    CALL                            1
                        4210    POP_TOP                         
                        4212    LOAD_FAST                       1: window
                        4214    LOAD_METHOD                     35: destroy
                        4236    PRECALL                         0
                        4240    CALL                            0
                        4250    POP_TOP                         
                        4252    LOAD_CONST                      0: None
                        4254    RETURN_VALUE                    
                [Code]
                    File Name: jetvam.pyw
                    Object Name: meliSmsLink
                    Qualified Name: MyApp.meliSmsLink
                    Arg Count: 2
                    Pos Only Arg Count: 0
                    KW Only Arg Count: 0
                    Stack Size: 8
                    Flags: 0x00000003 (CO_OPTIMIZED | CO_NEWLOCALS)
                    [Names]
                        'text_sms'
                        'config'
                        'delete'
                        'END'
                        'len'
                        'insert'
                        'server_domain'
                    [Locals+Names]
                        'self'
                        'text'
                    [Constants]
                        None
                        'normal'
                        (
                            'state'
                        )
                        '1.0'
                        11
                        'لطفا شماره موبایل را به طور کامل وارد کنید'
                        'tag-right'
                        'داخل نرم افزار فوروارد پیام که در زیر اسم آن آمده است تنظیمات را طبق مقادیر زیر وارد کنید'
                        '\n\n\n\nApp: sms Forwarder\n\nMode: URL\n\nURL: '
                        '/'
                        '/\n\nmethod: GET\n\n\nهمچنین می‌توانید مود نرم افزار را روی حالت پیامک قرار دهید. و پیامک های بانک را به سامانه ۱۰۰۰۰۶۰۶۰۰۶۶۰ فوروارد نمایید'
                        'disabled'
                    [Disassembly]
                        0       RESUME                          0
                        2       LOAD_FAST                       0: self
                        4       LOAD_ATTR                       0: text_sms
                        14      LOAD_METHOD                     1: config
                        36      LOAD_CONST                      1: 'normal'
                        38      KW_NAMES                        2: ('state',)
                        40      PRECALL                         1
                        44      CALL                            1
                        54      POP_TOP                         
                        56      LOAD_FAST                       0: self
                        58      LOAD_ATTR                       0: text_sms
                        68      LOAD_METHOD                     2: delete
                        90      LOAD_CONST                      3: '1.0'
                        92      LOAD_GLOBAL                     6: END
                        104     PRECALL                         2
                        108     CALL                            2
                        118     POP_TOP                         
                        120     LOAD_GLOBAL                     9: NULL + len
                        132     LOAD_FAST                       1: text
                        134     PRECALL                         1
                        138     CALL                            1
                        148     LOAD_CONST                      4: 11
                        150     COMPARE_OP                      0 (<)
                        156     POP_JUMP_FORWARD_IF_FALSE       29 (to 216)
                        158     LOAD_FAST                       0: self
                        160     LOAD_ATTR                       0: text_sms
                        170     LOAD_METHOD                     5: insert
                        192     LOAD_CONST                      3: '1.0'
                        194     LOAD_CONST                      5: 'لطفا شماره موبایل را به طور کامل وارد کنید'
                        196     LOAD_CONST                      6: 'tag-right'
                        198     PRECALL                         3
                        202     CALL                            3
                        212     POP_TOP                         
                        214     JUMP_FORWARD                    72 (to 360)
                        216     LOAD_FAST                       0: self
                        218     LOAD_ATTR                       0: text_sms
                        228     LOAD_METHOD                     5: insert
                        250     LOAD_CONST                      3: '1.0'
                        252     LOAD_CONST                      7: 'داخل نرم افزار فوروارد پیام که در زیر اسم آن آمده است تنظیمات را طبق مقادیر زیر وارد کنید'
                        254     LOAD_CONST                      6: 'tag-right'
                        256     PRECALL                         3
                        260     CALL                            3
                        270     POP_TOP                         
                        272     LOAD_FAST                       0: self
                        274     LOAD_ATTR                       0: text_sms
                        284     LOAD_METHOD                     5: insert
                        306     LOAD_GLOBAL                     6: END
                        318     LOAD_CONST                      8: '\n\n\n\nApp: sms Forwarder\n\nMode: URL\n\nURL: '
                        320     LOAD_GLOBAL                     12: server_domain
                        332     FORMAT_VALUE                    0 (FVC_NONE)
                        334     LOAD_CONST                      9: '/'
                        336     LOAD_FAST                       1: text
                        338     FORMAT_VALUE                    0 (FVC_NONE)
                        340     LOAD_CONST                      10: '/\n\nmethod: GET\n\n\nهمچنین می‌توانید مود نرم افزار را روی حالت پیامک قرار دهید. و پیامک های بانک را به سامانه ۱۰۰۰۰۶۰۶۰۰۶۶۰ فوروارد نمایید'
                        342     BUILD_STRING                    5
                        344     PRECALL                         2
                        348     CALL                            2
                        358     POP_TOP                         
                        360     LOAD_FAST                       0: self
                        362     LOAD_ATTR                       0: text_sms
                        372     LOAD_METHOD                     1: config
                        394     LOAD_CONST                      11: 'disabled'
                        396     KW_NAMES                        2: ('state',)
                        398     PRECALL                         1
                        402     CALL                            1
                        412     POP_TOP                         
                        414     LOAD_CONST                      0: None
                        416     RETURN_VALUE                    
                True
                [Code]
                    File Name: jetvam.pyw
                    Object Name: clearAll
                    Qualified Name: MyApp.clearAll
                    Arg Count: 2
                    Pos Only Arg Count: 0
                    KW Only Arg Count: 0
                    Stack Size: 4
                    Flags: 0x00000003 (CO_OPTIMIZED | CO_NEWLOCALS)
                    [Names]
                        'entry_motaqazian'
                        'delete'
                        'END'
                        'entry_sabt_nam'
                        'entry_code_meli'
                        'entry_code_meli_malek'
                        'entry_ostan'
                        'entry_shahr'
                        'entry_day_tavalod'
                        'entry_month_tavalod'
                        'entry_year_tavalod'
                        'entry_day_exdevaj'
                        'entry_month_ezdevaj'
                        'entry_year_exdevaj'
                        'entry_name'
                        'entry_family'
                        'entry_pedar'
                        'entry_sabet'
                        'entry_hamrah'
                        'entry_meli_hamsar'
                        'entry_posti'
                        'entry_neshani'
                        'entry_yaddasht'
                        'entry_bank_entekhabi'
                        'len'
                        'selected_bank_list'
                        'unselected_bank_list'
                        'entry_email'
                        'entry_code_shobe'
                        'entry_rahgiri'
                        'config'
                        'entry_alarm_bank'
                        'selected_bank_list_alarm'
                        'unselected_bank_list_alarm'
                        'bank_baz'
                        'entry_captcha'
                        'entry_sms'
                        'var_vaziat_shobe'
                        'set'
                        'entry_priority'
                    [Locals+Names]
                        'self'
                        'clear_top'
                    [Constants]
                        None
                        0
                        '------'
                        (
                            'text'
                        )
                    [Disassembly]
                        0       RESUME                          0
                        2       LOAD_FAST                       1: clear_top
                        4       POP_JUMP_FORWARD_IF_FALSE       64 (to 134)
                        6       LOAD_FAST                       0: self
                        8       LOAD_ATTR                       0: entry_motaqazian
                        18      LOAD_METHOD                     1: delete
                        40      LOAD_CONST                      1: 0
                        42      LOAD_GLOBAL                     4: END
                        54      PRECALL                         2
                        58      CALL                            2
                        68      POP_TOP                         
                        70      LOAD_FAST                       0: self
                        72      LOAD_ATTR                       3: entry_sabt_nam
                        82      LOAD_METHOD                     1: delete
                        104     LOAD_CONST                      1: 0
                        106     LOAD_GLOBAL                     4: END
                        118     PRECALL                         2
                        122     CALL                            2
                        132     POP_TOP                         
                        134     LOAD_FAST                       0: self
                        136     LOAD_ATTR                       4: entry_code_meli
                        146     LOAD_METHOD                     1: delete
                        168     LOAD_CONST                      1: 0
                        170     LOAD_GLOBAL                     4: END
                        182     PRECALL                         2
                        186     CALL                            2
                        196     POP_TOP                         
                        198     LOAD_FAST                       0: self
                        200     LOAD_ATTR                       5: entry_code_meli_malek
                        210     LOAD_METHOD                     1: delete
                        232     LOAD_CONST                      1: 0
                        234     LOAD_GLOBAL                     4: END
                        246     PRECALL                         2
                        250     CALL                            2
                        260     POP_TOP                         
                        262     LOAD_FAST                       0: self
                        264     LOAD_ATTR                       6: entry_ostan
                        274     LOAD_METHOD                     1: delete
                        296     LOAD_CONST                      1: 0
                        298     LOAD_GLOBAL                     4: END
                        310     PRECALL                         2
                        314     CALL                            2
                        324     POP_TOP                         
                        326     LOAD_FAST                       0: self
                        328     LOAD_ATTR                       7: entry_shahr
                        338     LOAD_METHOD                     1: delete
                        360     LOAD_CONST                      1: 0
                        362     LOAD_GLOBAL                     4: END
                        374     PRECALL                         2
                        378     CALL                            2
                        388     POP_TOP                         
                        390     LOAD_FAST                       0: self
                        392     LOAD_ATTR                       8: entry_day_tavalod
                        402     LOAD_METHOD                     1: delete
                        424     LOAD_CONST                      1: 0
                        426     LOAD_GLOBAL                     4: END
                        438     PRECALL                         2
                        442     CALL                            2
                        452     POP_TOP                         
                        454     LOAD_FAST                       0: self
                        456     LOAD_ATTR                       9: entry_month_tavalod
                        466     LOAD_METHOD                     1: delete
                        488     LOAD_CONST                      1: 0
                        490     LOAD_GLOBAL                     4: END
                        502     PRECALL                         2
                        506     CALL                            2
                        516     POP_TOP                         
                        518     LOAD_FAST                       0: self
                        520     LOAD_ATTR                       10: entry_year_tavalod
                        530     LOAD_METHOD                     1: delete
                        552     LOAD_CONST                      1: 0
                        554     LOAD_GLOBAL                     4: END
                        566     PRECALL                         2
                        570     CALL                            2
                        580     POP_TOP                         
                        582     LOAD_FAST                       0: self
                        584     LOAD_ATTR                       11: entry_day_exdevaj
                        594     LOAD_METHOD                     1: delete
                        616     LOAD_CONST                      1: 0
                        618     LOAD_GLOBAL                     4: END
                        630     PRECALL                         2
                        634     CALL                            2
                        644     POP_TOP                         
                        646     LOAD_FAST                       0: self
                        648     LOAD_ATTR                       12: entry_month_ezdevaj
                        658     LOAD_METHOD                     1: delete
                        680     LOAD_CONST                      1: 0
                        682     LOAD_GLOBAL                     4: END
                        694     PRECALL                         2
                        698     CALL                            2
                        708     POP_TOP                         
                        710     LOAD_FAST                       0: self
                        712     LOAD_ATTR                       13: entry_year_exdevaj
                        722     LOAD_METHOD                     1: delete
                        744     LOAD_CONST                      1: 0
                        746     LOAD_GLOBAL                     4: END
                        758     PRECALL                         2
                        762     CALL                            2
                        772     POP_TOP                         
                        774     LOAD_FAST                       0: self
                        776     LOAD_ATTR                       14: entry_name
                        786     LOAD_METHOD                     1: delete
                        808     LOAD_CONST                      1: 0
                        810     LOAD_GLOBAL                     4: END
                        822     PRECALL                         2
                        826     CALL                            2
                        836     POP_TOP                         
                        838     LOAD_FAST                       0: self
                        840     LOAD_ATTR                       15: entry_family
                        850     LOAD_METHOD                     1: delete
                        872     LOAD_CONST                      1: 0
                        874     LOAD_GLOBAL                     4: END
                        886     PRECALL                         2
                        890     CALL                            2
                        900     POP_TOP                         
                        902     LOAD_FAST                       0: self
                        904     LOAD_ATTR                       16: entry_pedar
                        914     LOAD_METHOD                     1: delete
                        936     LOAD_CONST                      1: 0
                        938     LOAD_GLOBAL                     4: END
                        950     PRECALL                         2
                        954     CALL                            2
                        964     POP_TOP                         
                        966     LOAD_FAST                       0: self
                        968     LOAD_ATTR                       17: entry_sabet
                        978     LOAD_METHOD                     1: delete
                        1000    LOAD_CONST                      1: 0
                        1002    LOAD_GLOBAL                     4: END
                        1014    PRECALL                         2
                        1018    CALL                            2
                        1028    POP_TOP                         
                        1030    LOAD_FAST                       0: self
                        1032    LOAD_ATTR                       18: entry_hamrah
                        1042    LOAD_METHOD                     1: delete
                        1064    LOAD_CONST                      1: 0
                        1066    LOAD_GLOBAL                     4: END
                        1078    PRECALL                         2
                        1082    CALL                            2
                        1092    POP_TOP                         
                        1094    LOAD_FAST                       0: self
                        1096    LOAD_ATTR                       19: entry_meli_hamsar
                        1106    LOAD_METHOD                     1: delete
                        1128    LOAD_CONST                      1: 0
                        1130    LOAD_GLOBAL                     4: END
                        1142    PRECALL                         2
                        1146    CALL                            2
                        1156    POP_TOP                         
                        1158    LOAD_FAST                       0: self
                        1160    LOAD_ATTR                       20: entry_posti
                        1170    LOAD_METHOD                     1: delete
                        1192    LOAD_CONST                      1: 0
                        1194    LOAD_GLOBAL                     4: END
                        1206    PRECALL                         2
                        1210    CALL                            2
                        1220    POP_TOP                         
                        1222    LOAD_FAST                       0: self
                        1224    LOAD_ATTR                       21: entry_neshani
                        1234    LOAD_METHOD                     1: delete
                        1256    LOAD_CONST                      1: 0
                        1258    LOAD_GLOBAL                     4: END
                        1270    PRECALL                         2
                        1274    CALL                            2
                        1284    POP_TOP                         
                        1286    LOAD_FAST                       0: self
                        1288    LOAD_ATTR                       22: entry_yaddasht
                        1298    LOAD_METHOD                     1: delete
                        1320    LOAD_CONST                      1: 0
                        1322    LOAD_GLOBAL                     4: END
                        1334    PRECALL                         2
                        1338    CALL                            2
                        1348    POP_TOP                         
                        1350    LOAD_FAST                       0: self
                        1352    LOAD_ATTR                       23: entry_bank_entekhabi
                        1362    LOAD_METHOD                     1: delete
                        1384    LOAD_CONST                      1: 0
                        1386    LOAD_GLOBAL                     4: END
                        1398    PRECALL                         2
                        1402    CALL                            2
                        1412    POP_TOP                         
                        1414    LOAD_GLOBAL                     49: NULL + len
                        1426    LOAD_FAST                       0: self
                        1428    LOAD_ATTR                       25: selected_bank_list
                        1438    PRECALL                         1
                        1442    CALL                            1
                        1452    POP_JUMP_FORWARD_IF_FALSE       21 (to 1496)
                        1454    LOAD_FAST                       0: self
                        1456    COPY                            1
                        1458    LOAD_ATTR                       26: unselected_bank_list
                        1468    LOAD_FAST                       0: self
                        1470    LOAD_ATTR                       25: selected_bank_list
                        1480    BINARY_OP                       13 (+=)
                        1484    SWAP                            2
                        1486    STORE_ATTR                      26: unselected_bank_list
                        1496    BUILD_LIST                      0
                        1498    LOAD_FAST                       0: self
                        1500    STORE_ATTR                      25: selected_bank_list
                        1510    LOAD_FAST                       0: self
                        1512    LOAD_ATTR                       27: entry_email
                        1522    LOAD_METHOD                     1: delete
                        1544    LOAD_CONST                      1: 0
                        1546    LOAD_GLOBAL                     4: END
                        1558    PRECALL                         2
                        1562    CALL                            2
                        1572    POP_TOP                         
                        1574    LOAD_FAST                       0: self
                        1576    LOAD_ATTR                       28: entry_code_shobe
                        1586    LOAD_METHOD                     1: delete
                        1608    LOAD_CONST                      1: 0
                        1610    LOAD_GLOBAL                     4: END
                        1622    PRECALL                         2
                        1626    CALL                            2
                        1636    POP_TOP                         
                        1638    LOAD_FAST                       0: self
                        1640    LOAD_ATTR                       29: entry_rahgiri
                        1650    LOAD_METHOD                     30: config
                        1672    LOAD_CONST                      2: '------'
                        1674    KW_NAMES                        3: ('text',)
                        1676    PRECALL                         1
                        1680    CALL                            1
                        1690    POP_TOP                         
                        1692    LOAD_FAST                       0: self
                        1694    LOAD_ATTR                       31: entry_alarm_bank
                        1704    LOAD_METHOD                     1: delete
                        1726    LOAD_CONST                      1: 0
                        1728    LOAD_GLOBAL                     4: END
                        1740    PRECALL                         2
                        1744    CALL                            2
                        1754    POP_TOP                         
                        1756    LOAD_GLOBAL                     49: NULL + len
                        1768    LOAD_FAST                       0: self
                        1770    LOAD_ATTR                       32: selected_bank_list_alarm
                        1780    PRECALL                         1
                        1784    CALL                            1
                        1794    POP_JUMP_FORWARD_IF_FALSE       21 (to 1838)
                        1796    LOAD_FAST                       0: self
                        1798    COPY                            1
                        1800    LOAD_ATTR                       33: unselected_bank_list_alarm
                        1810    LOAD_FAST                       0: self
                        1812    LOAD_ATTR                       32: selected_bank_list_alarm
                        1822    BINARY_OP                       13 (+=)
                        1826    SWAP                            2
                        1828    STORE_ATTR                      33: unselected_bank_list_alarm
                        1838    BUILD_LIST                      0
                        1840    LOAD_FAST                       0: self
                        1842    STORE_ATTR                      32: selected_bank_list_alarm
                        1852    LOAD_FAST                       0: self
                        1854    LOAD_ATTR                       34: bank_baz
                        1864    LOAD_METHOD                     30: config
                        1886    LOAD_CONST                      2: '------'
                        1888    KW_NAMES                        3: ('text',)
                        1890    PRECALL                         1
                        1894    CALL                            1
                        1904    POP_TOP                         
                        1906    LOAD_FAST                       0: self
                        1908    LOAD_ATTR                       35: entry_captcha
                        1918    LOAD_METHOD                     1: delete
                        1940    LOAD_CONST                      1: 0
                        1942    LOAD_GLOBAL                     4: END
                        1954    PRECALL                         2
                        1958    CALL                            2
                        1968    POP_TOP                         
                        1970    LOAD_FAST                       0: self
                        1972    LOAD_ATTR                       36: entry_sms
                        1982    LOAD_METHOD                     1: delete
                        2004    LOAD_CONST                      1: 0
                        2006    LOAD_GLOBAL                     4: END
                        2018    PRECALL                         2
                        2022    CALL                            2
                        2032    POP_TOP                         
                        2034    LOAD_FAST                       0: self
                        2036    LOAD_ATTR                       37: var_vaziat_shobe
                        2046    LOAD_METHOD                     38: set
                        2068    LOAD_CONST                      1: 0
                        2070    PRECALL                         1
                        2074    CALL                            1
                        2084    POP_TOP                         
                        2086    LOAD_FAST                       0: self
                        2088    LOAD_ATTR                       39: entry_priority
                        2098    LOAD_METHOD                     1: delete
                        2120    LOAD_CONST                      1: 0
                        2122    LOAD_GLOBAL                     4: END
                        2134    PRECALL                         2
                        2138    CALL                            2
                        2148    POP_TOP                         
                        2150    LOAD_CONST                      0: None
                        2152    RETURN_VALUE                    
                [Code]
                    File Name: jetvam.pyw
                    Object Name: clearStuf
                    Qualified Name: MyApp.clearStuf
                    Arg Count: 2
                    Pos Only Arg Count: 0
                    KW Only Arg Count: 0
                    Stack Size: 4
                    Flags: 0x00000003 (CO_OPTIMIZED | CO_NEWLOCALS)
                    [Names]
                        'entry_motaqazian'
                        'delete'
                        'END'
                        'entry_sabt_nam'
                        'entry_code_meli'
                        'entry_code_meli_malek'
                        'entry_day_tavalod'
                        'entry_month_tavalod'
                        'entry_year_tavalod'
                        'entry_hamrah'
                        'entry_rahgiri'
                        'config'
                    [Locals+Names]
                        'self'
                        'clear_top'
                    [Constants]
                        None
                        0
                        '------'
                        (
                            'text'
                        )
                    [Disassembly]
                        0       RESUME                          0
                        2       LOAD_FAST                       1: clear_top
                        4       POP_JUMP_FORWARD_IF_FALSE       64 (to 134)
                        6       LOAD_FAST                       0: self
                        8       LOAD_ATTR                       0: entry_motaqazian
                        18      LOAD_METHOD                     1: delete
                        40      LOAD_CONST                      1: 0
                        42      LOAD_GLOBAL                     4: END
                        54      PRECALL                         2
                        58      CALL                            2
                        68      POP_TOP                         
                        70      LOAD_FAST                       0: self
                        72      LOAD_ATTR                       3: entry_sabt_nam
                        82      LOAD_METHOD                     1: delete
                        104     LOAD_CONST                      1: 0
                        106     LOAD_GLOBAL                     4: END
                        118     PRECALL                         2
                        122     CALL                            2
                        132     POP_TOP                         
                        134     LOAD_FAST                       0: self
                        136     LOAD_ATTR                       4: entry_code_meli
                        146     LOAD_METHOD                     1: delete
                        168     LOAD_CONST                      1: 0
                        170     LOAD_GLOBAL                     4: END
                        182     PRECALL                         2
                        186     CALL                            2
                        196     POP_TOP                         
                        198     LOAD_FAST                       0: self
                        200     LOAD_ATTR                       5: entry_code_meli_malek
                        210     LOAD_METHOD                     1: delete
                        232     LOAD_CONST                      1: 0
                        234     LOAD_GLOBAL                     4: END
                        246     PRECALL                         2
                        250     CALL                            2
                        260     POP_TOP                         
                        262     LOAD_FAST                       0: self
                        264     LOAD_ATTR                       6: entry_day_tavalod
                        274     LOAD_METHOD                     1: delete
                        296     LOAD_CONST                      1: 0
                        298     LOAD_GLOBAL                     4: END
                        310     PRECALL                         2
                        314     CALL                            2
                        324     POP_TOP                         
                        326     LOAD_FAST                       0: self
                        328     LOAD_ATTR                       7: entry_month_tavalod
                        338     LOAD_METHOD                     1: delete
                        360     LOAD_CONST                      1: 0
                        362     LOAD_GLOBAL                     4: END
                        374     PRECALL                         2
                        378     CALL                            2
                        388     POP_TOP                         
                        390     LOAD_FAST                       0: self
                        392     LOAD_ATTR                       8: entry_year_tavalod
                        402     LOAD_METHOD                     1: delete
                        424     LOAD_CONST                      1: 0
                        426     LOAD_GLOBAL                     4: END
                        438     PRECALL                         2
                        442     CALL                            2
                        452     POP_TOP                         
                        454     LOAD_FAST                       0: self
                        456     LOAD_ATTR                       9: entry_hamrah
                        466     LOAD_METHOD                     1: delete
                        488     LOAD_CONST                      1: 0
                        490     LOAD_GLOBAL                     4: END
                        502     PRECALL                         2
                        506     CALL                            2
                        516     POP_TOP                         
                        518     LOAD_FAST                       0: self
                        520     LOAD_ATTR                       10: entry_rahgiri
                        530     LOAD_METHOD                     11: config
                        552     LOAD_CONST                      2: '------'
                        554     KW_NAMES                        3: ('text',)
                        556     PRECALL                         1
                        560     CALL                            1
                        570     POP_TOP                         
                        572     LOAD_CONST                      0: None
                        574     RETURN_VALUE                    
                [Code]
                    File Name: jetvam.pyw
                    Object Name: removeMember
                    Qualified Name: MyApp.removeMember
                    Arg Count: 1
                    Pos Only Arg Count: 0
                    KW Only Arg Count: 0
                    Stack Size: 7
                    Flags: 0x00000003 (CO_OPTIMIZED | CO_NEWLOCALS)
                    [Names]
                        'getMemberByMeli'
                        'val_meli'
                        'sqlite3'
                        'connect'
                        'cursor'
                        'execute'
                        'commit'
                        'close'
                        'notification'
                        'make'
                        'printError'
                        'getAllDataFromDataBase'
                        'database_list_motaqazi_index'
                        'entry_motaqazian'
                        'database_list_sabtname_index'
                        'entry_sabt_nam'
                        'label_motaqazian_num'
                        'config'
                        'str'
                        'len'
                        'clearAll'
                    [Locals+Names]
                        'self'
                        'con'
                        'cur'
                        'motaqazian_text_list'
                        'sabt_name_text_list'
                    [Constants]
                        None
                        'members.db'
                        "INSERT INTO deleted_members SELECT * FROM members WHERE meli='"
                        "'"
                        "UPDATE deleted_members SET rahgiri='------', status=0 WHERE meli='"
                        "DELETE FROM members WHERE meli='"
                        'هشدار'
                        'کاربر با کد ملی وارد شده حذف گردید'
                        [Code]
                            File Name: jetvam.pyw
                            Object Name: <listcomp>
                            Qualified Name: MyApp.removeMember.<locals>.<listcomp>
                            Arg Count: 1
                            Pos Only Arg Count: 0
                            KW Only Arg Count: 0
                            Stack Size: 10
                            Flags: 0x00000013 (CO_OPTIMIZED | CO_NEWLOCALS | CO_NESTED)
                            [Names]
                                'database_list'
                                'database_map'
                                'split'
                            [Locals+Names]
                                '.0'
                                'i'
                                'self'
                            [Constants]
                                'name'
                                '_'
                                'family'
                                'bank'
                                ','
                                0
                                '_('
                                ')'
                            [Disassembly]
                                0       COPY_FREE_VARS                  1
                                2       RESUME                          0
                                4       BUILD_LIST                      0
                                6       LOAD_FAST                       0: .0
                                8       FOR_ITER                        125 (to 260)
                                10      STORE_FAST                      1: i
                                12      LOAD_DEREF                      2: self
                                14      LOAD_ATTR                       0: database_list
                                24      LOAD_FAST                       1: i
                                26      BINARY_SUBSCR                   
                                36      LOAD_DEREF                      2: self
                                38      LOAD_ATTR                       1: database_map
                                48      LOAD_CONST                      0: 'name'
                                50      BINARY_SUBSCR                   
                                60      BINARY_SUBSCR                   
                                70      FORMAT_VALUE                    0 (FVC_NONE)
                                72      LOAD_CONST                      1: '_'
                                74      LOAD_DEREF                      2: self
                                76      LOAD_ATTR                       0: database_list
                                86      LOAD_FAST                       1: i
                                88      BINARY_SUBSCR                   
                                98      LOAD_DEREF                      2: self
                                100     LOAD_ATTR                       1: database_map
                                110     LOAD_CONST                      2: 'family'
                                112     BINARY_SUBSCR                   
                                122     BINARY_SUBSCR                   
                                132     FORMAT_VALUE                    0 (FVC_NONE)
                                134     LOAD_CONST                      1: '_'
                                136     LOAD_DEREF                      2: self
                                138     LOAD_ATTR                       0: database_list
                                148     LOAD_FAST                       1: i
                                150     BINARY_SUBSCR                   
                                160     LOAD_DEREF                      2: self
                                162     LOAD_ATTR                       1: database_map
                                172     LOAD_CONST                      3: 'bank'
                                174     BINARY_SUBSCR                   
                                184     BINARY_SUBSCR                   
                                194     LOAD_METHOD                     2: split
                                216     LOAD_CONST                      4: ','
                                218     PRECALL                         1
                                222     CALL                            1
                                232     LOAD_CONST                      5: 0
                                234     BINARY_SUBSCR                   
                                244     FORMAT_VALUE                    0 (FVC_NONE)
                                246     LOAD_CONST                      6: '_('
                                248     LOAD_FAST                       1: i
                                250     FORMAT_VALUE                    0 (FVC_NONE)
                                252     LOAD_CONST                      7: ')'
                                254     BUILD_STRING                    8
                                256     LIST_APPEND                     2
                                258     JUMP_BACKWARD                   126 (to 8)
                                260     RETURN_VALUE                    
                        'values'
                        [Code]
                            File Name: jetvam.pyw
                            Object Name: <listcomp>
                            Qualified Name: MyApp.removeMember.<locals>.<listcomp>
                            Arg Count: 1
                            Pos Only Arg Count: 0
                            KW Only Arg Count: 0
                            Stack Size: 10
                            Flags: 0x00000013 (CO_OPTIMIZED | CO_NEWLOCALS | CO_NESTED)
                            [Names]
                                'database_list'
                                'database_map'
                                'split'
                            [Locals+Names]
                                '.0'
                                'i'
                                'self'
                            [Constants]
                                'name'
                                '_'
                                'family'
                                'bank'
                                ','
                                0
                                '_('
                                ')'
                            [Disassembly]
                                0       COPY_FREE_VARS                  1
                                2       RESUME                          0
                                4       BUILD_LIST                      0
                                6       LOAD_FAST                       0: .0
                                8       FOR_ITER                        125 (to 260)
                                10      STORE_FAST                      1: i
                                12      LOAD_DEREF                      2: self
                                14      LOAD_ATTR                       0: database_list
                                24      LOAD_FAST                       1: i
                                26      BINARY_SUBSCR                   
                                36      LOAD_DEREF                      2: self
                                38      LOAD_ATTR                       1: database_map
                                48      LOAD_CONST                      0: 'name'
                                50      BINARY_SUBSCR                   
                                60      BINARY_SUBSCR                   
                                70      FORMAT_VALUE                    0 (FVC_NONE)
                                72      LOAD_CONST                      1: '_'
                                74      LOAD_DEREF                      2: self
                                76      LOAD_ATTR                       0: database_list
                                86      LOAD_FAST                       1: i
                                88      BINARY_SUBSCR                   
                                98      LOAD_DEREF                      2: self
                                100     LOAD_ATTR                       1: database_map
                                110     LOAD_CONST                      2: 'family'
                                112     BINARY_SUBSCR                   
                                122     BINARY_SUBSCR                   
                                132     FORMAT_VALUE                    0 (FVC_NONE)
                                134     LOAD_CONST                      1: '_'
                                136     LOAD_DEREF                      2: self
                                138     LOAD_ATTR                       0: database_list
                                148     LOAD_FAST                       1: i
                                150     BINARY_SUBSCR                   
                                160     LOAD_DEREF                      2: self
                                162     LOAD_ATTR                       1: database_map
                                172     LOAD_CONST                      3: 'bank'
                                174     BINARY_SUBSCR                   
                                184     BINARY_SUBSCR                   
                                194     LOAD_METHOD                     2: split
                                216     LOAD_CONST                      4: ','
                                218     PRECALL                         1
                                222     CALL                            1
                                232     LOAD_CONST                      5: 0
                                234     BINARY_SUBSCR                   
                                244     FORMAT_VALUE                    0 (FVC_NONE)
                                246     LOAD_CONST                      6: '_('
                                248     LOAD_FAST                       1: i
                                250     FORMAT_VALUE                    0 (FVC_NONE)
                                252     LOAD_CONST                      7: ')'
                                254     BUILD_STRING                    8
                                256     LIST_APPEND                     2
                                258     JUMP_BACKWARD                   126 (to 8)
                                260     RETURN_VALUE                    
                        (
                            'text'
                        )
                        'خطا'
                        'کد ملی مورد نظر یافت نشد'
                    [Disassembly]
                        0       MAKE_CELL                       0: self
                        2       RESUME                          0
                        4       LOAD_DEREF                      0: self
                        6       LOAD_METHOD                     0: getMemberByMeli
                        28      LOAD_DEREF                      0: self
                        30      LOAD_ATTR                       1: val_meli
                        40      PRECALL                         1
                        44      CALL                            1
                        54      POP_JUMP_FORWARD_IF_FALSE       370 (to 798)
                        58      LOAD_GLOBAL                     5: NULL + sqlite3
                        70      LOAD_ATTR                       3: connect
                        80      LOAD_CONST                      1: 'members.db'
                        82      PRECALL                         1
                        86      CALL                            1
                        96      STORE_FAST                      1: con
                        98      LOAD_FAST                       1: con
                        100     LOAD_METHOD                     4: cursor
                        122     PRECALL                         0
                        126     CALL                            0
                        136     STORE_FAST                      2: cur
                        138     LOAD_FAST                       2: cur
                        140     LOAD_METHOD                     5: execute
                        162     LOAD_CONST                      2: "INSERT INTO deleted_members SELECT * FROM members WHERE meli='"
                        164     LOAD_DEREF                      0: self
                        166     LOAD_ATTR                       1: val_meli
                        176     FORMAT_VALUE                    0 (FVC_NONE)
                        178     LOAD_CONST                      3: "'"
                        180     BUILD_STRING                    3
                        182     PRECALL                         1
                        186     CALL                            1
                        196     POP_TOP                         
                        198     LOAD_FAST                       2: cur
                        200     LOAD_METHOD                     5: execute
                        222     LOAD_CONST                      4: "UPDATE deleted_members SET rahgiri='------', status=0 WHERE meli='"
                        224     LOAD_DEREF                      0: self
                        226     LOAD_ATTR                       1: val_meli
                        236     FORMAT_VALUE                    0 (FVC_NONE)
                        238     LOAD_CONST                      3: "'"
                        240     BUILD_STRING                    3
                        242     PRECALL                         1
                        246     CALL                            1
                        256     POP_TOP                         
                        258     LOAD_FAST                       2: cur
                        260     LOAD_METHOD                     5: execute
                        282     LOAD_CONST                      5: "DELETE FROM members WHERE meli='"
                        284     LOAD_DEREF                      0: self
                        286     LOAD_ATTR                       1: val_meli
                        296     FORMAT_VALUE                    0 (FVC_NONE)
                        298     LOAD_CONST                      3: "'"
                        300     BUILD_STRING                    3
                        302     PRECALL                         1
                        306     CALL                            1
                        316     POP_TOP                         
                        318     LOAD_FAST                       1: con
                        320     LOAD_METHOD                     6: commit
                        342     PRECALL                         0
                        346     CALL                            0
                        356     POP_TOP                         
                        358     LOAD_FAST                       1: con
                        360     LOAD_METHOD                     7: close
                        382     PRECALL                         0
                        386     CALL                            0
                        396     POP_TOP                         
                        398     LOAD_GLOBAL                     17: NULL + notification
                        410     LOAD_ATTR                       9: make
                        420     LOAD_CONST                      6: 'هشدار'
                        422     LOAD_CONST                      7: 'کاربر با کد ملی وارد شده حذف گردید'
                        424     PRECALL                         2
                        428     CALL                            2
                        438     POP_TOP                         
                        440     LOAD_DEREF                      0: self
                        442     LOAD_METHOD                     10: printError
                        464     LOAD_CONST                      7: 'کاربر با کد ملی وارد شده حذف گردید'
                        466     PRECALL                         1
                        470     CALL                            1
                        480     POP_TOP                         
                        482     LOAD_DEREF                      0: self
                        484     LOAD_METHOD                     11: getAllDataFromDataBase
                        506     PRECALL                         0
                        510     CALL                            0
                        520     POP_TOP                         
                        522     LOAD_CLOSURE                    0: self
                        524     BUILD_TUPLE                     1
                        526     LOAD_CONST                      8: <CODE> <listcomp>
                        528     MAKE_FUNCTION                   8
                        530     LOAD_DEREF                      0: self
                        532     LOAD_ATTR                       12: database_list_motaqazi_index
                        542     GET_ITER                        
                        544     PRECALL                         0
                        548     CALL                            0
                        558     STORE_FAST                      3: motaqazian_text_list
                        560     LOAD_FAST                       3: motaqazian_text_list
                        562     LOAD_DEREF                      0: self
                        564     LOAD_ATTR                       13: entry_motaqazian
                        574     LOAD_CONST                      9: 'values'
                        576     STORE_SUBSCR                    
                        580     LOAD_CLOSURE                    0: self
                        582     BUILD_TUPLE                     1
                        584     LOAD_CONST                      10: <CODE> <listcomp>
                        586     MAKE_FUNCTION                   8
                        588     LOAD_DEREF                      0: self
                        590     LOAD_ATTR                       14: database_list_sabtname_index
                        600     GET_ITER                        
                        602     PRECALL                         0
                        606     CALL                            0
                        616     STORE_FAST                      4: sabt_name_text_list
                        618     LOAD_FAST                       4: sabt_name_text_list
                        620     LOAD_DEREF                      0: self
                        622     LOAD_ATTR                       15: entry_sabt_nam
                        632     LOAD_CONST                      9: 'values'
                        634     STORE_SUBSCR                    
                        638     LOAD_DEREF                      0: self
                        640     LOAD_ATTR                       16: label_motaqazian_num
                        650     LOAD_METHOD                     17: config
                        672     LOAD_GLOBAL                     37: NULL + str
                        684     LOAD_GLOBAL                     39: NULL + len
                        696     LOAD_DEREF                      0: self
                        698     LOAD_ATTR                       12: database_list_motaqazi_index
                        708     PRECALL                         1
                        712     CALL                            1
                        722     PRECALL                         1
                        726     CALL                            1
                        736     KW_NAMES                        11: ('text',)
                        738     PRECALL                         1
                        742     CALL                            1
                        752     POP_TOP                         
                        754     LOAD_DEREF                      0: self
                        756     LOAD_METHOD                     20: clearAll
                        778     PRECALL                         0
                        782     CALL                            0
                        792     POP_TOP                         
                        794     LOAD_CONST                      0: None
                        796     RETURN_VALUE                    
                        798     LOAD_GLOBAL                     17: NULL + notification
                        810     LOAD_ATTR                       9: make
                        820     LOAD_CONST                      12: 'خطا'
                        822     LOAD_CONST                      13: 'کد ملی مورد نظر یافت نشد'
                        824     PRECALL                         2
                        828     CALL                            2
                        838     POP_TOP                         
                        840     LOAD_DEREF                      0: self
                        842     LOAD_METHOD                     10: printError
                        864     LOAD_CONST                      13: 'کد ملی مورد نظر یافت نشد'
                        866     PRECALL                         1
                        870     CALL                            1
                        880     POP_TOP                         
                        882     LOAD_CONST                      0: None
                        884     RETURN_VALUE                    
                [Code]
                    File Name: jetvam.pyw
                    Object Name: updatePriority
                    Qualified Name: MyApp.updatePriority
                    Arg Count: 4
                    Pos Only Arg Count: 0
                    KW Only Arg Count: 0
                    Stack Size: 9
                    Flags: 0x00000003 (CO_OPTIMIZED | CO_NEWLOCALS)
                    [Names]
                        'len'
                        'list'
                        'execute'
                    [Locals+Names]
                        'self'
                        'cursor'
                        'meli'
                        'priority'
                    [Constants]
                        None
                        'SELECT * FROM priority WHERE meli="'
                        '"'
                        1
                        'UPDATE priority SET priority="'
                        '" WHERE meli="'
                        'INSERT INTO priority VALUES (NULL, ?, ?)'
                    [Disassembly]
                        0       RESUME                          0
                        2       LOAD_GLOBAL                     1: NULL + len
                        14      LOAD_GLOBAL                     3: NULL + list
                        26      LOAD_FAST                       1: cursor
                        28      LOAD_METHOD                     2: execute
                        50      LOAD_CONST                      1: 'SELECT * FROM priority WHERE meli="'
                        52      LOAD_FAST                       2: meli
                        54      FORMAT_VALUE                    0 (FVC_NONE)
                        56      LOAD_CONST                      2: '"'
                        58      BUILD_STRING                    3
                        60      PRECALL                         1
                        64      CALL                            1
                        74      PRECALL                         1
                        78      CALL                            1
                        88      PRECALL                         1
                        92      CALL                            1
                        102     LOAD_CONST                      3: 1
                        104     COMPARE_OP                      2 (==)
                        110     POP_JUMP_FORWARD_IF_FALSE       30 (to 172)
                        112     LOAD_FAST                       1: cursor
                        114     LOAD_METHOD                     2: execute
                        136     LOAD_CONST                      4: 'UPDATE priority SET priority="'
                        138     LOAD_FAST                       3: priority
                        140     FORMAT_VALUE                    0 (FVC_NONE)
                        142     LOAD_CONST                      5: '" WHERE meli="'
                        144     LOAD_FAST                       2: meli
                        146     FORMAT_VALUE                    0 (FVC_NONE)
                        148     LOAD_CONST                      2: '"'
                        150     BUILD_STRING                    5
                        152     PRECALL                         1
                        156     CALL                            1
                        166     POP_TOP                         
                        168     LOAD_CONST                      0: None
                        170     RETURN_VALUE                    
                        172     LOAD_FAST                       1: cursor
                        174     LOAD_METHOD                     2: execute
                        196     LOAD_CONST                      6: 'INSERT INTO priority VALUES (NULL, ?, ?)'
                        198     LOAD_FAST                       2: meli
                        200     LOAD_FAST                       3: priority
                        202     BUILD_TUPLE                     2
                        204     PRECALL                         2
                        208     CALL                            2
                        218     POP_TOP                         
                        220     LOAD_CONST                      0: None
                        222     RETURN_VALUE                    
                [Code]
                    File Name: jetvam.pyw
                    Object Name: addMember
                    Qualified Name: MyApp.addMember
                    Arg Count: 1
                    Pos Only Arg Count: 0
                    KW Only Arg Count: 0
                    Stack Size: 29
                    Flags: 0x00000003 (CO_OPTIMIZED | CO_NEWLOCALS)
                    [Names]
                        'getFormData'
                        'len'
                        'val_meli'
                        'notification'
                        'make'
                        'printError'
                        'sqlite3'
                        'connect'
                        'cursor'
                        'val_malek'
                        'val_ostan'
                        'val_shahr'
                        'val_birth_day'
                        'val_birth_month'
                        'val_birth_year'
                        'val_marry_day'
                        'val_marry_month'
                        'val_marry_year'
                        'val_name'
                        'val_family'
                        'val_pedar'
                        'val_sabet'
                        'val_hamrah'
                        'val_hamsar'
                        'val_posti'
                        'val_neshani'
                        'val_yaddasht'
                        'val_bank'
                        'val_email'
                        'val_shobe'
                        'val_vaziat_shobe'
                        'val_rahgiri'
                        'val_jensiat'
                        'val_isar'
                        'val_sarbazi'
                        'val_tabeiat'
                        'getMemberByMeli'
                        'execute'
                        'val_bank_alarm'
                        'updatePriority'
                        'entry_priority'
                        'get'
                        'commit'
                        'close'
                        'getAllDataFromDataBase'
                        'database_list_motaqazi_index'
                        'entry_motaqazian'
                        'database_list_sabtname_index'
                        'entry_sabt_nam'
                        'label_motaqazian_num'
                        'config'
                        'str'
                        'database_map'
                    [Locals+Names]
                        'self'
                        'con'
                        'cur'
                        'data'
                        'user'
                        'motaqazian_text_list'
                        'sabt_name_text_list'
                    [Constants]
                        '"id", "meli", "malek", "ostan", "shahr","""""""""""""""""""" "name", "family", \n            "pedar", "sabet", "hamrah", "hamsar", "posti", "neshani", \n            "yaddasht", "bank", "email", "shobe", "vaziat-shobe", \n            "rahgiri", "jensiat", "isar", "sarbazi", "tabeiat", "status"'
                        10
                        'خطا'
                        'کد ملی حتما باید تکمیل شود'
                        None
                        'members.db'
                        0
                        False
                        'INSERT INTO members VALUES (NULL, ?, ?, ?, ?, ?, ?, ?, ?, ?, ?, ?, ?, ?, ?, ?, ?, ?, ?, ?, ?, ?, ?, ?, ?, ?, ?, ?, ?, ?)'
                        'DELETE FROM banks_alarm WHERE meli='
                        'INSERT INTO banks_alarm VALUES (NULL, ?, ?)'
                        [Code]
                            File Name: jetvam.pyw
                            Object Name: <listcomp>
                            Qualified Name: MyApp.addMember.<locals>.<listcomp>
                            Arg Count: 1
                            Pos Only Arg Count: 0
                            KW Only Arg Count: 0
                            Stack Size: 10
                            Flags: 0x00000013 (CO_OPTIMIZED | CO_NEWLOCALS | CO_NESTED)
                            [Names]
                                'database_list'
                                'database_map'
                                'split'
                            [Locals+Names]
                                '.0'
                                'i'
                                'self'
                            [Constants]
                                'name'
                                '_'
                                'family'
                                'bank'
                                ','
                                0
                                '_('
                                ')'
                            [Disassembly]
                                0       COPY_FREE_VARS                  1
                                2       RESUME                          0
                                4       BUILD_LIST                      0
                                6       LOAD_FAST                       0: .0
                                8       FOR_ITER                        125 (to 260)
                                10      STORE_FAST                      1: i
                                12      LOAD_DEREF                      2: self
                                14      LOAD_ATTR                       0: database_list
                                24      LOAD_FAST                       1: i
                                26      BINARY_SUBSCR                   
                                36      LOAD_DEREF                      2: self
                                38      LOAD_ATTR                       1: database_map
                                48      LOAD_CONST                      0: 'name'
                                50      BINARY_SUBSCR                   
                                60      BINARY_SUBSCR                   
                                70      FORMAT_VALUE                    0 (FVC_NONE)
                                72      LOAD_CONST                      1: '_'
                                74      LOAD_DEREF                      2: self
                                76      LOAD_ATTR                       0: database_list
                                86      LOAD_FAST                       1: i
                                88      BINARY_SUBSCR                   
                                98      LOAD_DEREF                      2: self
                                100     LOAD_ATTR                       1: database_map
                                110     LOAD_CONST                      2: 'family'
                                112     BINARY_SUBSCR                   
                                122     BINARY_SUBSCR                   
                                132     FORMAT_VALUE                    0 (FVC_NONE)
                                134     LOAD_CONST                      1: '_'
                                136     LOAD_DEREF                      2: self
                                138     LOAD_ATTR                       0: database_list
                                148     LOAD_FAST                       1: i
                                150     BINARY_SUBSCR                   
                                160     LOAD_DEREF                      2: self
                                162     LOAD_ATTR                       1: database_map
                                172     LOAD_CONST                      3: 'bank'
                                174     BINARY_SUBSCR                   
                                184     BINARY_SUBSCR                   
                                194     LOAD_METHOD                     2: split
                                216     LOAD_CONST                      4: ','
                                218     PRECALL                         1
                                222     CALL                            1
                                232     LOAD_CONST                      5: 0
                                234     BINARY_SUBSCR                   
                                244     FORMAT_VALUE                    0 (FVC_NONE)
                                246     LOAD_CONST                      6: '_('
                                248     LOAD_FAST                       1: i
                                250     FORMAT_VALUE                    0 (FVC_NONE)
                                252     LOAD_CONST                      7: ')'
                                254     BUILD_STRING                    8
                                256     LIST_APPEND                     2
                                258     JUMP_BACKWARD                   126 (to 8)
                                260     RETURN_VALUE                    
                        'values'
                        [Code]
                            File Name: jetvam.pyw
                            Object Name: <listcomp>
                            Qualified Name: MyApp.addMember.<locals>.<listcomp>
                            Arg Count: 1
                            Pos Only Arg Count: 0
                            KW Only Arg Count: 0
                            Stack Size: 10
                            Flags: 0x00000013 (CO_OPTIMIZED | CO_NEWLOCALS | CO_NESTED)
                            [Names]
                                'database_list'
                                'database_map'
                                'split'
                            [Locals+Names]
                                '.0'
                                'i'
                                'self'
                            [Constants]
                                'name'
                                '_'
                                'family'
                                'bank'
                                ','
                                0
                                '_('
                                ')'
                            [Disassembly]
                                0       COPY_FREE_VARS                  1
                                2       RESUME                          0
                                4       BUILD_LIST                      0
                                6       LOAD_FAST                       0: .0
                                8       FOR_ITER                        125 (to 260)
                                10      STORE_FAST                      1: i
                                12      LOAD_DEREF                      2: self
                                14      LOAD_ATTR                       0: database_list
                                24      LOAD_FAST                       1: i
                                26      BINARY_SUBSCR                   
                                36      LOAD_DEREF                      2: self
                                38      LOAD_ATTR                       1: database_map
                                48      LOAD_CONST                      0: 'name'
                                50      BINARY_SUBSCR                   
                                60      BINARY_SUBSCR                   
                                70      FORMAT_VALUE                    0 (FVC_NONE)
                                72      LOAD_CONST                      1: '_'
                                74      LOAD_DEREF                      2: self
                                76      LOAD_ATTR                       0: database_list
                                86      LOAD_FAST                       1: i
                                88      BINARY_SUBSCR                   
                                98      LOAD_DEREF                      2: self
                                100     LOAD_ATTR                       1: database_map
                                110     LOAD_CONST                      2: 'family'
                                112     BINARY_SUBSCR                   
                                122     BINARY_SUBSCR                   
                                132     FORMAT_VALUE                    0 (FVC_NONE)
                                134     LOAD_CONST                      1: '_'
                                136     LOAD_DEREF                      2: self
                                138     LOAD_ATTR                       0: database_list
                                148     LOAD_FAST                       1: i
                                150     BINARY_SUBSCR                   
                                160     LOAD_DEREF                      2: self
                                162     LOAD_ATTR                       1: database_map
                                172     LOAD_CONST                      3: 'bank'
                                174     BINARY_SUBSCR                   
                                184     BINARY_SUBSCR                   
                                194     LOAD_METHOD                     2: split
                                216     LOAD_CONST                      4: ','
                                218     PRECALL                         1
                                222     CALL                            1
                                232     LOAD_CONST                      5: 0
                                234     BINARY_SUBSCR                   
                                244     FORMAT_VALUE                    0 (FVC_NONE)
                                246     LOAD_CONST                      6: '_('
                                248     LOAD_FAST                       1: i
                                250     FORMAT_VALUE                    0 (FVC_NONE)
                                252     LOAD_CONST                      7: ')'
                                254     BUILD_STRING                    8
                                256     LIST_APPEND                     2
                                258     JUMP_BACKWARD                   126 (to 8)
                                260     RETURN_VALUE                    
                        (
                            'text'
                        )
                        'عملیات موفق'
                        'مشخصات کاربر مورد نظر شما ثبت شد'
                        'status'
                        1
                        'عملیات نا موفق'
                        'کد ملی وارد شده قبلا ذخیره همچنین ثبت نام شده است و امکان تغیرات وجود ندارد'
                        "DELETE FROM members WHERE id='"
                        'id'
                        "'"
                        [Code]
                            File Name: jetvam.pyw
                            Object Name: <listcomp>
                            Qualified Name: MyApp.addMember.<locals>.<listcomp>
                            Arg Count: 1
                            Pos Only Arg Count: 0
                            KW Only Arg Count: 0
                            Stack Size: 10
                            Flags: 0x00000013 (CO_OPTIMIZED | CO_NEWLOCALS | CO_NESTED)
                            [Names]
                                'database_list'
                                'database_map'
                                'split'
                            [Locals+Names]
                                '.0'
                                'i'
                                'self'
                            [Constants]
                                'name'
                                '_'
                                'family'
                                'bank'
                                ','
                                0
                                '_('
                                ')'
                            [Disassembly]
                                0       COPY_FREE_VARS                  1
                                2       RESUME                          0
                                4       BUILD_LIST                      0
                                6       LOAD_FAST                       0: .0
                                8       FOR_ITER                        125 (to 260)
                                10      STORE_FAST                      1: i
                                12      LOAD_DEREF                      2: self
                                14      LOAD_ATTR                       0: database_list
                                24      LOAD_FAST                       1: i
                                26      BINARY_SUBSCR                   
                                36      LOAD_DEREF                      2: self
                                38      LOAD_ATTR                       1: database_map
                                48      LOAD_CONST                      0: 'name'
                                50      BINARY_SUBSCR                   
                                60      BINARY_SUBSCR                   
                                70      FORMAT_VALUE                    0 (FVC_NONE)
                                72      LOAD_CONST                      1: '_'
                                74      LOAD_DEREF                      2: self
                                76      LOAD_ATTR                       0: database_list
                                86      LOAD_FAST                       1: i
                                88      BINARY_SUBSCR                   
                                98      LOAD_DEREF                      2: self
                                100     LOAD_ATTR                       1: database_map
                                110     LOAD_CONST                      2: 'family'
                                112     BINARY_SUBSCR                   
                                122     BINARY_SUBSCR                   
                                132     FORMAT_VALUE                    0 (FVC_NONE)
                                134     LOAD_CONST                      1: '_'
                                136     LOAD_DEREF                      2: self
                                138     LOAD_ATTR                       0: database_list
                                148     LOAD_FAST                       1: i
                                150     BINARY_SUBSCR                   
                                160     LOAD_DEREF                      2: self
                                162     LOAD_ATTR                       1: database_map
                                172     LOAD_CONST                      3: 'bank'
                                174     BINARY_SUBSCR                   
                                184     BINARY_SUBSCR                   
                                194     LOAD_METHOD                     2: split
                                216     LOAD_CONST                      4: ','
                                218     PRECALL                         1
                                222     CALL                            1
                                232     LOAD_CONST                      5: 0
                                234     BINARY_SUBSCR                   
                                244     FORMAT_VALUE                    0 (FVC_NONE)
                                246     LOAD_CONST                      6: '_('
                                248     LOAD_FAST                       1: i
                                250     FORMAT_VALUE                    0 (FVC_NONE)
                                252     LOAD_CONST                      7: ')'
                                254     BUILD_STRING                    8
                                256     LIST_APPEND                     2
                                258     JUMP_BACKWARD                   126 (to 8)
                                260     RETURN_VALUE                    
                        [Code]
                            File Name: jetvam.pyw
                            Object Name: <listcomp>
                            Qualified Name: MyApp.addMember.<locals>.<listcomp>
                            Arg Count: 1
                            Pos Only Arg Count: 0
                            KW Only Arg Count: 0
                            Stack Size: 10
                            Flags: 0x00000013 (CO_OPTIMIZED | CO_NEWLOCALS | CO_NESTED)
                            [Names]
                                'database_list'
                                'database_map'
                                'split'
                            [Locals+Names]
                                '.0'
                                'i'
                                'self'
                            [Constants]
                                'name'
                                '_'
                                'family'
                                'bank'
                                ','
                                0
                                '_('
                                ')'
                            [Disassembly]
                                0       COPY_FREE_VARS                  1
                                2       RESUME                          0
                                4       BUILD_LIST                      0
                                6       LOAD_FAST                       0: .0
                                8       FOR_ITER                        125 (to 260)
                                10      STORE_FAST                      1: i
                                12      LOAD_DEREF                      2: self
                                14      LOAD_ATTR                       0: database_list
                                24      LOAD_FAST                       1: i
                                26      BINARY_SUBSCR                   
                                36      LOAD_DEREF                      2: self
                                38      LOAD_ATTR                       1: database_map
                                48      LOAD_CONST                      0: 'name'
                                50      BINARY_SUBSCR                   
                                60      BINARY_SUBSCR                   
                                70      FORMAT_VALUE                    0 (FVC_NONE)
                                72      LOAD_CONST                      1: '_'
                                74      LOAD_DEREF                      2: self
                                76      LOAD_ATTR                       0: database_list
                                86      LOAD_FAST                       1: i
                                88      BINARY_SUBSCR                   
                                98      LOAD_DEREF                      2: self
                                100     LOAD_ATTR                       1: database_map
                                110     LOAD_CONST                      2: 'family'
                                112     BINARY_SUBSCR                   
                                122     BINARY_SUBSCR                   
                                132     FORMAT_VALUE                    0 (FVC_NONE)
                                134     LOAD_CONST                      1: '_'
                                136     LOAD_DEREF                      2: self
                                138     LOAD_ATTR                       0: database_list
                                148     LOAD_FAST                       1: i
                                150     BINARY_SUBSCR                   
                                160     LOAD_DEREF                      2: self
                                162     LOAD_ATTR                       1: database_map
                                172     LOAD_CONST                      3: 'bank'
                                174     BINARY_SUBSCR                   
                                184     BINARY_SUBSCR                   
                                194     LOAD_METHOD                     2: split
                                216     LOAD_CONST                      4: ','
                                218     PRECALL                         1
                                222     CALL                            1
                                232     LOAD_CONST                      5: 0
                                234     BINARY_SUBSCR                   
                                244     FORMAT_VALUE                    0 (FVC_NONE)
                                246     LOAD_CONST                      6: '_('
                                248     LOAD_FAST                       1: i
                                250     FORMAT_VALUE                    0 (FVC_NONE)
                                252     LOAD_CONST                      7: ')'
                                254     BUILD_STRING                    8
                                256     LIST_APPEND                     2
                                258     JUMP_BACKWARD                   126 (to 8)
                                260     RETURN_VALUE                    
                        'مشخصات کاربر مورد نظر بروزرسانی شد'
                    [Disassembly]
                        0       MAKE_CELL                       0: self
                        2       RESUME                          0
                        4       LOAD_DEREF                      0: self
                        6       LOAD_METHOD                     0: getFormData
                        28      PRECALL                         0
                        32      CALL                            0
                        42      POP_TOP                         
                        44      LOAD_GLOBAL                     3: NULL + len
                        56      LOAD_DEREF                      0: self
                        58      LOAD_ATTR                       2: val_meli
                        68      PRECALL                         1
                        72      CALL                            1
                        82      LOAD_CONST                      1: 10
                        84      COMPARE_OP                      3 (!=)
                        90      POP_JUMP_FORWARD_IF_FALSE       44 (to 180)
                        92      LOAD_GLOBAL                     7: NULL + notification
                        104     LOAD_ATTR                       4: make
                        114     LOAD_CONST                      2: 'خطا'
                        116     LOAD_CONST                      3: 'کد ملی حتما باید تکمیل شود'
                        118     PRECALL                         2
                        122     CALL                            2
                        132     POP_TOP                         
                        134     LOAD_DEREF                      0: self
                        136     LOAD_METHOD                     5: printError
                        158     LOAD_CONST                      3: 'کد ملی حتما باید تکمیل شود'
                        160     PRECALL                         1
                        164     CALL                            1
                        174     POP_TOP                         
                        176     LOAD_CONST                      4: None
                        178     RETURN_VALUE                    
                        180     LOAD_GLOBAL                     13: NULL + sqlite3
                        192     LOAD_ATTR                       7: connect
                        202     LOAD_CONST                      5: 'members.db'
                        204     PRECALL                         1
                        208     CALL                            1
                        218     STORE_FAST                      1: con
                        220     LOAD_FAST                       1: con
                        222     LOAD_METHOD                     8: cursor
                        244     PRECALL                         0
                        248     CALL                            0
                        258     STORE_FAST                      2: cur
                        260     LOAD_DEREF                      0: self
                        262     LOAD_ATTR                       2: val_meli
                        272     LOAD_DEREF                      0: self
                        274     LOAD_ATTR                       9: val_malek
                        284     LOAD_DEREF                      0: self
                        286     LOAD_ATTR                       10: val_ostan
                        296     LOAD_DEREF                      0: self
                        298     LOAD_ATTR                       11: val_shahr
                        308     LOAD_DEREF                      0: self
                        310     LOAD_ATTR                       12: val_birth_day
                        320     LOAD_DEREF                      0: self
                        322     LOAD_ATTR                       13: val_birth_month
                        332     LOAD_DEREF                      0: self
                        334     LOAD_ATTR                       14: val_birth_year
                        344     LOAD_DEREF                      0: self
                        346     LOAD_ATTR                       15: val_marry_day
                        356     LOAD_DEREF                      0: self
                        358     LOAD_ATTR                       16: val_marry_month
                        368     LOAD_DEREF                      0: self
                        370     LOAD_ATTR                       17: val_marry_year
                        380     LOAD_DEREF                      0: self
                        382     LOAD_ATTR                       18: val_name
                        392     LOAD_DEREF                      0: self
                        394     LOAD_ATTR                       19: val_family
                        404     LOAD_DEREF                      0: self
                        406     LOAD_ATTR                       20: val_pedar
                        416     LOAD_DEREF                      0: self
                        418     LOAD_ATTR                       21: val_sabet
                        428     LOAD_DEREF                      0: self
                        430     LOAD_ATTR                       22: val_hamrah
                        440     LOAD_DEREF                      0: self
                        442     LOAD_ATTR                       23: val_hamsar
                        452     LOAD_DEREF                      0: self
                        454     LOAD_ATTR                       24: val_posti
                        464     LOAD_DEREF                      0: self
                        466     LOAD_ATTR                       25: val_neshani
                        476     LOAD_DEREF                      0: self
                        478     LOAD_ATTR                       26: val_yaddasht
                        488     LOAD_DEREF                      0: self
                        490     LOAD_ATTR                       27: val_bank
                        500     LOAD_DEREF                      0: self
                        502     LOAD_ATTR                       28: val_email
                        512     LOAD_DEREF                      0: self
                        514     LOAD_ATTR                       29: val_shobe
                        524     LOAD_DEREF                      0: self
                        526     LOAD_ATTR                       30: val_vaziat_shobe
                        536     LOAD_DEREF                      0: self
                        538     LOAD_ATTR                       31: val_rahgiri
                        548     LOAD_DEREF                      0: self
                        550     LOAD_ATTR                       32: val_jensiat
                        560     LOAD_DEREF                      0: self
                        562     LOAD_ATTR                       33: val_isar
                        572     LOAD_DEREF                      0: self
                        574     LOAD_ATTR                       34: val_sarbazi
                        584     LOAD_DEREF                      0: self
                        586     LOAD_ATTR                       35: val_tabeiat
                        596     LOAD_CONST                      6: 0
                        598     BUILD_TUPLE                     29
                        600     STORE_FAST                      3: data
                        602     LOAD_DEREF                      0: self
                        604     LOAD_METHOD                     36: getMemberByMeli
                        626     LOAD_DEREF                      0: self
                        628     LOAD_ATTR                       2: val_meli
                        638     PRECALL                         1
                        642     CALL                            1
                        652     STORE_FAST                      4: user
                        654     LOAD_FAST                       4: user
                        656     LOAD_CONST                      7: False
                        658     COMPARE_OP                      2 (==)
                        664     POP_JUMP_FORWARD_IF_FALSE       356 (to 1380)
                        668     LOAD_FAST                       2: cur
                        670     LOAD_METHOD                     37: execute
                        692     LOAD_CONST                      8: 'INSERT INTO members VALUES (NULL, ?, ?, ?, ?, ?, ?, ?, ?, ?, ?, ?, ?, ?, ?, ?, ?, ?, ?, ?, ?, ?, ?, ?, ?, ?, ?, ?, ?, ?)'
                        694     LOAD_FAST                       3: data
                        696     PRECALL                         2
                        700     CALL                            2
                        710     POP_TOP                         
                        712     LOAD_FAST                       2: cur
                        714     LOAD_METHOD                     37: execute
                        736     LOAD_CONST                      9: 'DELETE FROM banks_alarm WHERE meli='
                        738     LOAD_DEREF                      0: self
                        740     LOAD_ATTR                       2: val_meli
                        750     FORMAT_VALUE                    0 (FVC_NONE)
                        752     BUILD_STRING                    2
                        754     PRECALL                         1
                        758     CALL                            1
                        768     POP_TOP                         
                        770     LOAD_FAST                       2: cur
                        772     LOAD_METHOD                     37: execute
                        794     LOAD_CONST                      10: 'INSERT INTO banks_alarm VALUES (NULL, ?, ?)'
                        796     LOAD_DEREF                      0: self
                        798     LOAD_ATTR                       2: val_meli
                        808     LOAD_DEREF                      0: self
                        810     LOAD_ATTR                       38: val_bank_alarm
                        820     BUILD_TUPLE                     2
                        822     PRECALL                         2
                        826     CALL                            2
                        836     POP_TOP                         
                        838     LOAD_DEREF                      0: self
                        840     LOAD_METHOD                     39: updatePriority
                        862     LOAD_FAST                       2: cur
                        864     LOAD_DEREF                      0: self
                        866     LOAD_ATTR                       2: val_meli
                        876     LOAD_DEREF                      0: self
                        878     LOAD_ATTR                       40: entry_priority
                        888     LOAD_METHOD                     41: get
                        910     PRECALL                         0
                        914     CALL                            0
                        924     PRECALL                         3
                        928     CALL                            3
                        938     POP_TOP                         
                        940     LOAD_FAST                       1: con
                        942     LOAD_METHOD                     42: commit
                        964     PRECALL                         0
                        968     CALL                            0
                        978     POP_TOP                         
                        980     LOAD_FAST                       1: con
                        982     LOAD_METHOD                     43: close
                        1004    PRECALL                         0
                        1008    CALL                            0
                        1018    POP_TOP                         
                        1020    LOAD_DEREF                      0: self
                        1022    LOAD_METHOD                     44: getAllDataFromDataBase
                        1044    PRECALL                         0
                        1048    CALL                            0
                        1058    POP_TOP                         
                        1060    LOAD_CLOSURE                    0: self
                        1062    BUILD_TUPLE                     1
                        1064    LOAD_CONST                      11: <CODE> <listcomp>
                        1066    MAKE_FUNCTION                   8
                        1068    LOAD_DEREF                      0: self
                        1070    LOAD_ATTR                       45: database_list_motaqazi_index
                        1080    GET_ITER                        
                        1082    PRECALL                         0
                        1086    CALL                            0
                        1096    STORE_FAST                      5: motaqazian_text_list
                        1098    LOAD_FAST                       5: motaqazian_text_list
                        1100    LOAD_DEREF                      0: self
                        1102    LOAD_ATTR                       46: entry_motaqazian
                        1112    LOAD_CONST                      12: 'values'
                        1114    STORE_SUBSCR                    
                        1118    LOAD_CLOSURE                    0: self
                        1120    BUILD_TUPLE                     1
                        1122    LOAD_CONST                      13: <CODE> <listcomp>
                        1124    MAKE_FUNCTION                   8
                        1126    LOAD_DEREF                      0: self
                        1128    LOAD_ATTR                       47: database_list_sabtname_index
                        1138    GET_ITER                        
                        1140    PRECALL                         0
                        1144    CALL                            0
                        1154    STORE_FAST                      6: sabt_name_text_list
                        1156    LOAD_FAST                       6: sabt_name_text_list
                        1158    LOAD_DEREF                      0: self
                        1160    LOAD_ATTR                       48: entry_sabt_nam
                        1170    LOAD_CONST                      12: 'values'
                        1172    STORE_SUBSCR                    
                        1176    LOAD_DEREF                      0: self
                        1178    LOAD_ATTR                       49: label_motaqazian_num
                        1188    LOAD_METHOD                     50: config
                        1210    LOAD_GLOBAL                     103: NULL + str
                        1222    LOAD_GLOBAL                     3: NULL + len
                        1234    LOAD_DEREF                      0: self
                        1236    LOAD_ATTR                       45: database_list_motaqazi_index
                        1246    PRECALL                         1
                        1250    CALL                            1
                        1260    PRECALL                         1
                        1264    CALL                            1
                        1274    KW_NAMES                        14: ('text',)
                        1276    PRECALL                         1
                        1280    CALL                            1
                        1290    POP_TOP                         
                        1292    LOAD_GLOBAL                     7: NULL + notification
                        1304    LOAD_ATTR                       4: make
                        1314    LOAD_CONST                      15: 'عملیات موفق'
                        1316    LOAD_CONST                      16: 'مشخصات کاربر مورد نظر شما ثبت شد'
                        1318    PRECALL                         2
                        1322    CALL                            2
                        1332    POP_TOP                         
                        1334    LOAD_DEREF                      0: self
                        1336    LOAD_METHOD                     5: printError
                        1358    LOAD_CONST                      16: 'مشخصات کاربر مورد نظر شما ثبت شد'
                        1360    PRECALL                         1
                        1364    CALL                            1
                        1374    POP_TOP                         
                        1376    LOAD_CONST                      4: None
                        1378    RETURN_VALUE                    
                        1380    LOAD_FAST                       4: user
                        1382    LOAD_DEREF                      0: self
                        1384    LOAD_ATTR                       52: database_map
                        1394    LOAD_CONST                      17: 'status'
                        1396    BINARY_SUBSCR                   
                        1406    BINARY_SUBSCR                   
                        1416    LOAD_CONST                      18: 1
                        1418    COMPARE_OP                      2 (==)
                        1424    POP_JUMP_FORWARD_IF_FALSE       44 (to 1514)
                        1426    LOAD_GLOBAL                     7: NULL + notification
                        1438    LOAD_ATTR                       4: make
                        1448    LOAD_CONST                      19: 'عملیات نا موفق'
                        1450    LOAD_CONST                      20: 'کد ملی وارد شده قبلا ذخیره همچنین ثبت نام شده است و امکان تغیرات وجود ندارد'
                        1452    PRECALL                         2
                        1456    CALL                            2
                        1466    POP_TOP                         
                        1468    LOAD_DEREF                      0: self
                        1470    LOAD_METHOD                     5: printError
                        1492    LOAD_CONST                      20: 'کد ملی وارد شده قبلا ذخیره همچنین ثبت نام شده است و امکان تغیرات وجود ندارد'
                        1494    PRECALL                         1
                        1498    CALL                            1
                        1508    POP_TOP                         
                        1510    LOAD_CONST                      4: None
                        1512    RETURN_VALUE                    
                        1514    LOAD_FAST                       2: cur
                        1516    LOAD_METHOD                     37: execute
                        1538    LOAD_CONST                      21: "DELETE FROM members WHERE id='"
                        1540    LOAD_FAST                       4: user
                        1542    LOAD_DEREF                      0: self
                        1544    LOAD_ATTR                       52: database_map
                        1554    LOAD_CONST                      22: 'id'
                        1556    BINARY_SUBSCR                   
                        1566    BINARY_SUBSCR                   
                        1576    FORMAT_VALUE                    0 (FVC_NONE)
                        1578    LOAD_CONST                      23: "'"
                        1580    BUILD_STRING                    3
                        1582    PRECALL                         1
                        1586    CALL                            1
                        1596    POP_TOP                         
                        1598    LOAD_FAST                       2: cur
                        1600    LOAD_METHOD                     37: execute
                        1622    LOAD_CONST                      8: 'INSERT INTO members VALUES (NULL, ?, ?, ?, ?, ?, ?, ?, ?, ?, ?, ?, ?, ?, ?, ?, ?, ?, ?, ?, ?, ?, ?, ?, ?, ?, ?, ?, ?, ?)'
                        1624    LOAD_FAST                       3: data
                        1626    PRECALL                         2
                        1630    CALL                            2
                        1640    POP_TOP                         
                        1642    LOAD_FAST                       2: cur
                        1644    LOAD_METHOD                     37: execute
                        1666    LOAD_CONST                      9: 'DELETE FROM banks_alarm WHERE meli='
                        1668    LOAD_DEREF                      0: self
                        1670    LOAD_ATTR                       2: val_meli
                        1680    FORMAT_VALUE                    0 (FVC_NONE)
                        1682    BUILD_STRING                    2
                        1684    PRECALL                         1
                        1688    CALL                            1
                        1698    POP_TOP                         
                        1700    LOAD_FAST                       2: cur
                        1702    LOAD_METHOD                     37: execute
                        1724    LOAD_CONST                      10: 'INSERT INTO banks_alarm VALUES (NULL, ?, ?)'
                        1726    LOAD_DEREF                      0: self
                        1728    LOAD_ATTR                       2: val_meli
                        1738    LOAD_DEREF                      0: self
                        1740    LOAD_ATTR                       38: val_bank_alarm
                        1750    BUILD_TUPLE                     2
                        1752    PRECALL                         2
                        1756    CALL                            2
                        1766    POP_TOP                         
                        1768    LOAD_DEREF                      0: self
                        1770    LOAD_METHOD                     39: updatePriority
                        1792    LOAD_FAST                       2: cur
                        1794    LOAD_DEREF                      0: self
                        1796    LOAD_ATTR                       2: val_meli
                        1806    LOAD_DEREF                      0: self
                        1808    LOAD_ATTR                       40: entry_priority
                        1818    LOAD_METHOD                     41: get
                        1840    PRECALL                         0
                        1844    CALL                            0
                        1854    PRECALL                         3
                        1858    CALL                            3
                        1868    POP_TOP                         
                        1870    LOAD_FAST                       1: con
                        1872    LOAD_METHOD                     42: commit
                        1894    PRECALL                         0
                        1898    CALL                            0
                        1908    POP_TOP                         
                        1910    LOAD_FAST                       1: con
                        1912    LOAD_METHOD                     43: close
                        1934    PRECALL                         0
                        1938    CALL                            0
                        1948    POP_TOP                         
                        1950    LOAD_DEREF                      0: self
                        1952    LOAD_METHOD                     44: getAllDataFromDataBase
                        1974    PRECALL                         0
                        1978    CALL                            0
                        1988    POP_TOP                         
                        1990    LOAD_CLOSURE                    0: self
                        1992    BUILD_TUPLE                     1
                        1994    LOAD_CONST                      24: <CODE> <listcomp>
                        1996    MAKE_FUNCTION                   8
                        1998    LOAD_DEREF                      0: self
                        2000    LOAD_ATTR                       45: database_list_motaqazi_index
                        2010    GET_ITER                        
                        2012    PRECALL                         0
                        2016    CALL                            0
                        2026    STORE_FAST                      5: motaqazian_text_list
                        2028    LOAD_FAST                       5: motaqazian_text_list
                        2030    LOAD_DEREF                      0: self
                        2032    LOAD_ATTR                       46: entry_motaqazian
                        2042    LOAD_CONST                      12: 'values'
                        2044    STORE_SUBSCR                    
                        2048    LOAD_CLOSURE                    0: self
                        2050    BUILD_TUPLE                     1
                        2052    LOAD_CONST                      25: <CODE> <listcomp>
                        2054    MAKE_FUNCTION                   8
                        2056    LOAD_DEREF                      0: self
                        2058    LOAD_ATTR                       47: database_list_sabtname_index
                        2068    GET_ITER                        
                        2070    PRECALL                         0
                        2074    CALL                            0
                        2084    STORE_FAST                      6: sabt_name_text_list
                        2086    LOAD_FAST                       6: sabt_name_text_list
                        2088    LOAD_DEREF                      0: self
                        2090    LOAD_ATTR                       48: entry_sabt_nam
                        2100    LOAD_CONST                      12: 'values'
                        2102    STORE_SUBSCR                    
                        2106    LOAD_GLOBAL                     7: NULL + notification
                        2118    LOAD_ATTR                       4: make
                        2128    LOAD_CONST                      15: 'عملیات موفق'
                        2130    LOAD_CONST                      26: 'مشخصات کاربر مورد نظر بروزرسانی شد'
                        2132    PRECALL                         2
                        2136    CALL                            2
                        2146    POP_TOP                         
                        2148    LOAD_DEREF                      0: self
                        2150    LOAD_METHOD                     5: printError
                        2172    LOAD_CONST                      26: 'مشخصات کاربر مورد نظر بروزرسانی شد'
                        2174    PRECALL                         1
                        2178    CALL                            1
                        2188    POP_TOP                         
                        2190    LOAD_CONST                      4: None
                        2192    RETURN_VALUE                    
                [Code]
                    File Name: jetvam.pyw
                    Object Name: refreshCAPTCHA
                    Qualified Name: MyApp.refreshCAPTCHA
                    Arg Count: 1
                    Pos Only Arg Count: 0
                    KW Only Arg Count: 0
                    Stack Size: 4
                    Flags: 0x00000003 (CO_OPTIMIZED | CO_NEWLOCALS)
                    [Names]
                        'settings'
                        'int'
                        'time'
                        'captcha_counter'
                        'automation'
                        'captcha_refresh_pending'
                    [Locals+Names]
