                                88      BINARY_SUBSCR                   
                                98      LOAD_DEREF                      2: self
                                100     LOAD_ATTR                       1: database_map
                                110     LOAD_CONST                      2: 'family'
                                112     BINARY_SUBSCR                   
                                122     BINARY_SUBSCR                   
                                132     FORMAT_VALUE                    0 (FVC_NONE)
                                134     LOAD_CONST                      1: '_'
                                136     LOAD_DEREF                      2: self
                                138     LOAD_ATTR                       0: database_list
                                148     LOAD_FAST                       1: i
                                150     BINARY_SUBSCR                   
                                160     LOAD_DEREF                      2: self
                                162     LOAD_ATTR                       1: database_map
                                172     LOAD_CONST                      3: 'bank'
                                174     BINARY_SUBSCR                   
                                184     BINARY_SUBSCR                   
                                194     LOAD_METHOD                     2: split
                                216     LOAD_CONST                      4: ','
                                218     PRECALL                         1
                                222     CALL                            1
                                232     LOAD_CONST                      5: 0
                                234     BINARY_SUBSCR                   
                                244     FORMAT_VALUE                    0 (FVC_NONE)
                                246     LOAD_CONST                      6: '_('
                                248     LOAD_FAST                       1: i
                                250     FORMAT_VALUE                    0 (FVC_NONE)
                                252     LOAD_CONST                      7: ')'
                                254     BUILD_STRING                    8
                                256     LIST_APPEND                     2
                                258     JUMP_BACKWARD                   126 (to 8)
                                260     RETURN_VALUE                    
                        'values'
                        [Code]
                            File Name: jetvam.pyw
                            Object Name: <listcomp>
                            Qualified Name: MyApp.restoreMember.<locals>.<listcomp>
                            Arg Count: 1
                            Pos Only Arg Count: 0
                            KW Only Arg Count: 0
                            Stack Size: 10
                            Flags: 0x00000013 (CO_OPTIMIZED | CO_NEWLOCALS | CO_NESTED)
                            [Names]
                                'database_list'
                                'database_map'
                                'split'
                            [Locals+Names]
                                '.0'
                                'i'
                                'self'
                            [Constants]
                                'name'
                                '_'
                                'family'
                                'bank'
                                ','
                                0
                                '_('
                                ')'
                            [Disassembly]
                                0       COPY_FREE_VARS                  1
                                2       RESUME                          0
                                4       BUILD_LIST                      0
                                6       LOAD_FAST                       0: .0
                                8       FOR_ITER                        125 (to 260)
                                10      STORE_FAST                      1: i
                                12      LOAD_DEREF                      2: self
                                14      LOAD_ATTR                       0: database_list
                                24      LOAD_FAST                       1: i
                                26      BINARY_SUBSCR                   
                                36      LOAD_DEREF                      2: self
                                38      LOAD_ATTR                       1: database_map
                                48      LOAD_CONST                      0: 'name'
                                50      BINARY_SUBSCR                   
                                60      BINARY_SUBSCR                   
                                70      FORMAT_VALUE                    0 (FVC_NONE)
                                72      LOAD_CONST                      1: '_'
                                74      LOAD_DEREF                      2: self
                                76      LOAD_ATTR                       0: database_list
                                86      LOAD_FAST                       1: i
                                88      BINARY_SUBSCR                   
                                98      LOAD_DEREF                      2: self
                                100     LOAD_ATTR                       1: database_map
                                110     LOAD_CONST                      2: 'family'
                                112     BINARY_SUBSCR                   
                                122     BINARY_SUBSCR                   
                                132     FORMAT_VALUE                    0 (FVC_NONE)
                                134     LOAD_CONST                      1: '_'
                                136     LOAD_DEREF                      2: self
                                138     LOAD_ATTR                       0: database_list
                                148     LOAD_FAST                       1: i
                                150     BINARY_SUBSCR                   
                                160     LOAD_DEREF                      2: self
                                162     LOAD_ATTR                       1: database_map
                                172     LOAD_CONST                      3: 'bank'
                                174     BINARY_SUBSCR                   
                                184     BINARY_SUBSCR                   
                                194     LOAD_METHOD                     2: split
                                216     LOAD_CONST                      4: ','
                                218     PRECALL                         1
                                222     CALL                            1
                                232     LOAD_CONST                      5: 0
                                234     BINARY_SUBSCR                   
                                244     FORMAT_VALUE                    0 (FVC_NONE)
                                246     LOAD_CONST                      6: '_('
                                248     LOAD_FAST                       1: i
                                250     FORMAT_VALUE                    0 (FVC_NONE)
                                252     LOAD_CONST                      7: ')'
                                254     BUILD_STRING                    8
                                256     LIST_APPEND                     2
                                258     JUMP_BACKWARD                   126 (to 8)
                                260     RETURN_VALUE                    
                        (
                            'text'
                        )
                        'بازیابی'
                        'کاربر با کد ملی '
                        ' بازیابی شد'
                    [Disassembly]
                        0       MAKE_CELL                       0: self
                        2       RESUME                          0
                        4       LOAD_CONST                      1: '_'
                        6       LOAD_FAST                       1: member
                        8       CONTAINS_OP                     1 (not in)
                        10      POP_JUMP_FORWARD_IF_FALSE       2 (to 16)
                        12      LOAD_CONST                      0: None
                        14      RETURN_VALUE                    
                        16      LOAD_FAST                       1: member
                        18      LOAD_METHOD                     0: split
                        40      LOAD_CONST                      1: '_'
                        42      PRECALL                         1
                        46      CALL                            1
                        56      LOAD_CONST                      2: -1
                        58      BINARY_SUBSCR                   
                        68      LOAD_METHOD                     1: replace
                        90      LOAD_CONST                      3: '('
                        92      LOAD_CONST                      4: ''
                        94      PRECALL                         2
                        98      CALL                            2
                        108     LOAD_METHOD                     1: replace
                        130     LOAD_CONST                      5: ')'
                        132     LOAD_CONST                      4: ''
                        134     PRECALL                         2
                        138     CALL                            2
                        148     STORE_FAST                      2: idxs
                        150     LOAD_FAST                       2: idxs
                        152     LOAD_METHOD                     0: split
                        174     LOAD_CONST                      6: ','
                        176     PRECALL                         1
                        180     CALL                            1
                        190     UNPACK_SEQUENCE                 2
                        194     STORE_FAST                      3: index
                        196     STORE_FAST                      4: id_code
                        198     LOAD_GLOBAL                     5: NULL + int
                        210     LOAD_FAST                       3: index
                        212     PRECALL                         1
                        216     CALL                            1
                        226     LOAD_GLOBAL                     5: NULL + int
                        238     LOAD_FAST                       4: id_code
                        240     PRECALL                         1
                        244     CALL                            1
                        254     STORE_FAST                      4: id_code
                        256     STORE_FAST                      3: index
                        258     LOAD_DEREF                      0: self
                        260     LOAD_ATTR                       3: database_list_removed_members
                        270     LOAD_FAST                       3: index
                        272     BINARY_SUBSCR                   
                        282     STORE_FAST                      1: member
                        284     LOAD_FAST                       1: member
                        286     LOAD_DEREF                      0: self
                        288     LOAD_ATTR                       4: database_map
                        298     LOAD_CONST                      7: 'meli'
                        300     BINARY_SUBSCR                   
                        310     BINARY_SUBSCR                   
                        320     STORE_FAST                      5: meli
                        322     LOAD_GLOBAL                     11: NULL + sqlite3
                        334     LOAD_ATTR                       6: connect
                        344     LOAD_CONST                      8: 'members.db'
                        346     PRECALL                         1
                        350     CALL                            1
                        360     STORE_FAST                      6: con
                        362     LOAD_FAST                       6: con
                        364     LOAD_METHOD                     7: cursor
                        386     PRECALL                         0
                        390     CALL                            0
                        400     STORE_FAST                      7: cur
                        402     LOAD_FAST                       7: cur
                        404     LOAD_METHOD                     8: execute
                        426     LOAD_CONST                      9: "INSERT INTO members SELECT * FROM deleted_members WHERE id='"
                        428     LOAD_FAST                       4: id_code
                        430     FORMAT_VALUE                    0 (FVC_NONE)
                        432     LOAD_CONST                      10: "'"
                        434     BUILD_STRING                    3
                        436     PRECALL                         1
                        440     CALL                            1
                        450     POP_TOP                         
                        452     LOAD_FAST                       7: cur
                        454     LOAD_METHOD                     8: execute
                        476     LOAD_CONST                      11: "DELETE FROM deleted_members WHERE id='"
                        478     LOAD_FAST                       4: id_code
                        480     FORMAT_VALUE                    0 (FVC_NONE)
                        482     LOAD_CONST                      10: "'"
                        484     BUILD_STRING                    3
                        486     PRECALL                         1
                        490     CALL                            1
                        500     POP_TOP                         
                        502     LOAD_FAST                       6: con
                        504     LOAD_METHOD                     9: commit
                        526     PRECALL                         0
                        530     CALL                            0
                        540     POP_TOP                         
                        542     LOAD_FAST                       6: con
                        544     LOAD_METHOD                     10: close
                        566     PRECALL                         0
                        570     CALL                            0
                        580     POP_TOP                         
                        582     LOAD_DEREF                      0: self
                        584     LOAD_METHOD                     11: getAllDataFromDataBase
                        606     PRECALL                         0
                        610     CALL                            0
                        620     POP_TOP                         
                        622     LOAD_CLOSURE                    0: self
                        624     BUILD_TUPLE                     1
                        626     LOAD_CONST                      12: <CODE> <listcomp>
                        628     MAKE_FUNCTION                   8
                        630     LOAD_DEREF                      0: self
                        632     LOAD_ATTR                       12: database_list_motaqazi_index
                        642     GET_ITER                        
                        644     PRECALL                         0
                        648     CALL                            0
                        658     STORE_FAST                      8: motaqazian_text_list
                        660     LOAD_FAST                       8: motaqazian_text_list
                        662     LOAD_DEREF                      0: self
                        664     LOAD_ATTR                       13: entry_motaqazian
                        674     LOAD_CONST                      13: 'values'
                        676     STORE_SUBSCR                    
                        680     LOAD_CLOSURE                    0: self
                        682     BUILD_TUPLE                     1
                        684     LOAD_CONST                      14: <CODE> <listcomp>
                        686     MAKE_FUNCTION                   8
                        688     LOAD_DEREF                      0: self
                        690     LOAD_ATTR                       14: database_list_sabtname_index
                        700     GET_ITER                        
                        702     PRECALL                         0
                        706     CALL                            0
                        716     STORE_FAST                      9: sabt_name_text_list
                        718     LOAD_FAST                       9: sabt_name_text_list
                        720     LOAD_DEREF                      0: self
                        722     LOAD_ATTR                       15: entry_sabt_nam
                        732     LOAD_CONST                      13: 'values'
                        734     STORE_SUBSCR                    
                        738     LOAD_DEREF                      0: self
                        740     LOAD_ATTR                       16: label_motaqazian_num
                        750     LOAD_METHOD                     17: config
                        772     LOAD_GLOBAL                     37: NULL + str
                        784     LOAD_GLOBAL                     39: NULL + len
                        796     LOAD_DEREF                      0: self
                        798     LOAD_ATTR                       12: database_list_motaqazi_index
                        808     PRECALL                         1
                        812     CALL                            1
                        822     PRECALL                         1
                        826     CALL                            1
                        836     KW_NAMES                        15: ('text',)
                        838     PRECALL                         1
                        842     CALL                            1
                        852     POP_TOP                         
                        854     LOAD_GLOBAL                     41: NULL + notification
                        866     LOAD_ATTR                       21: make
                        876     LOAD_CONST                      16: 'بازیابی'
                        878     LOAD_CONST                      17: 'کاربر با کد ملی '
                        880     LOAD_FAST                       5: meli
                        882     FORMAT_VALUE                    0 (FVC_NONE)
                        884     LOAD_CONST                      18: ' بازیابی شد'
                        886     BUILD_STRING                    3
                        888     PRECALL                         2
                        892     CALL                            2
                        902     POP_TOP                         
                        904     LOAD_DEREF                      0: self
                        906     LOAD_METHOD                     22: printError
                        928     LOAD_CONST                      17: 'کاربر با کد ملی '
                        930     LOAD_FAST                       5: meli
                        932     FORMAT_VALUE                    0 (FVC_NONE)
                        934     LOAD_CONST                      18: ' بازیابی شد'
                        936     BUILD_STRING                    3
                        938     PRECALL                         1
                        942     CALL                            1
                        952     POP_TOP                         
                        954     LOAD_CONST                      0: None
                        956     RETURN_VALUE                    
                [Code]
                    File Name: jetvam.pyw
                    Object Name: showBankSeletion_select
                    Qualified Name: MyApp.showBankSeletion_select
                    Arg Count: 2
                    Pos Only Arg Count: 0
                    KW Only Arg Count: 0
                    Stack Size: 5
                    Flags: 0x00000003 (CO_OPTIMIZED | CO_NEWLOCALS)
                    [Names]
                        'showBankSeletion'
                        'unselected_bank_list'
                        'selected_bank_list'
                    [Locals+Names]
                        'self'
                        '_'
                    [Constants]
                        None
                        'select'
                        (
                            'bank_list_'
                            'selected_bank_list_'
                            'mode'
                        )
                    [Disassembly]
                        0       RESUME                          0
                        2       LOAD_FAST                       0: self
                        4       LOAD_METHOD                     0: showBankSeletion
                        26      LOAD_FAST                       0: self
                        28      LOAD_ATTR                       1: unselected_bank_list
                        38      LOAD_FAST                       0: self
                        40      LOAD_ATTR                       2: selected_bank_list
                        50      LOAD_CONST                      1: 'select'
                        52      KW_NAMES                        2: ('bank_list_', 'selected_bank_list_', 'mode')
                        54      PRECALL                         3
                        58      CALL                            3
                        68      POP_TOP                         
                        70      LOAD_CONST                      0: None
                        72      RETURN_VALUE                    
                [Code]
                    File Name: jetvam.pyw
                    Object Name: showBankSeletion_alarm
                    Qualified Name: MyApp.showBankSeletion_alarm
                    Arg Count: 2
                    Pos Only Arg Count: 0
                    KW Only Arg Count: 0
                    Stack Size: 5
                    Flags: 0x00000003 (CO_OPTIMIZED | CO_NEWLOCALS)
                    [Names]
                        'showBankSeletion'
                        'unselected_bank_list_alarm'
                        'selected_bank_list_alarm'
                    [Locals+Names]
                        'self'
                        '_'
                    [Constants]
                        None
                        'alarm'
                        (
                            'bank_list_'
                            'selected_bank_list_'
                            'mode'
                        )
                    [Disassembly]
                        0       RESUME                          0
                        2       LOAD_FAST                       0: self
                        4       LOAD_METHOD                     0: showBankSeletion
                        26      LOAD_FAST                       0: self
                        28      LOAD_ATTR                       1: unselected_bank_list_alarm
                        38      LOAD_FAST                       0: self
                        40      LOAD_ATTR                       2: selected_bank_list_alarm
                        50      LOAD_CONST                      1: 'alarm'
                        52      KW_NAMES                        2: ('bank_list_', 'selected_bank_list_', 'mode')
                        54      PRECALL                         3
                        58      CALL                            3
                        68      POP_TOP                         
                        70      LOAD_CONST                      0: None
                        72      RETURN_VALUE                    
                [Code]
                    File Name: jetvam.pyw
                    Object Name: showBankSeletion
                    Qualified Name: MyApp.showBankSeletion
                    Arg Count: 5
                    Pos Only Arg Count: 0
                    KW Only Arg Count: 0
                    Stack Size: 8
                    Flags: 0x00000003 (CO_OPTIMIZED | CO_NEWLOCALS)
                    [Names]
                        'bank_select_windows'
                        'destroy'
                        'Tk'
                        'title'
                        'resizable'
                        'Grid'
                        'rowconfigure'
                        'columnconfigure'
                        'protocol'
                        'Treeview'
                        'selected_bank'
                        'heading'
                        'column'
                        'insert'
                        'unselected_bank'
                        'grid'
                        'Button'
                        'Scrollbar'
                        'VERTICAL'
                        'yview'
                        'configure'
                        'set'
                        'bind'
                        'selectBank'
                        'unselectBank'
                        'mainloop'
                    [Locals+Names]
                        'self'
                        '_'
                        'bank_list_'
                        'selected_bank_list_'
                        'mode'
                        'i'
                        'scrollbar'
                    [Constants]
                        None
                        'انتخاب بانک'
                        False
                        0
                        1
                        (
                            'weight'
                        )
                        'WM_DELETE_WINDOW'
                        'selected_bank'
                        'headings'
                        (
                            'columns'
                            'show'
                        )
                        'بانک های انتخاب شده'
                        (
                            'text'
                        )
                        'e'
                        (
                            'anchor'
                        )
                        ''
                        'end'
                        (
                            'text'
                            'values'
                        )
                        'bank_list'
                        'لیست بانک ها'
                        'nsew'
                        7
                        (
                            'column'
                            'row'
                            'sticky'
                            'padx'
                        )
                        2
                        'ذخیره'
                        [Code]
                            File Name: jetvam.pyw
                            Object Name: <lambda>
                            Qualified Name: MyApp.showBankSeletion.<locals>.<lambda>
                            Arg Count: 0
                            Pos Only Arg Count: 0
                            KW Only Arg Count: 0
                            Stack Size: 3
                            Flags: 0x00000013 (CO_OPTIMIZED | CO_NEWLOCALS | CO_NESTED)
                            [Names]
                                'closeDialogBank'
                            [Locals+Names]
                                'mode'
                                'self'
                            [Constants]
                                None
                            [Disassembly]
                                0       COPY_FREE_VARS                  2
                                2       RESUME                          0
                                4       LOAD_DEREF                      1: self
                                6       LOAD_METHOD                     0: closeDialogBank
                                28      LOAD_DEREF                      0: mode
                                30      PRECALL                         1
                                34      CALL                            1
                                44      RETURN_VALUE                    
                        (
                            'text'
                            'command'
                        )
                        4
                        'ew'
                        10
                        (
                            'row'
                            'column'
                            'columnspan'
                            'sticky'
                            'pady'
                            'padx'
                        )
                        (
                            'orient'
                            'command'
                        )
                        (
                            'yscroll'
                        )
                        'ns'
                        (
                            'row'
                            'column'
                            'sticky'
                        )
                        3
                        '<<TreeviewSelect>>'
                    [Disassembly]
                        0       MAKE_CELL                       0: self
                        2       MAKE_CELL                       4: mode
                        4       RESUME                          0
                        6       NOP                             
                        8       LOAD_DEREF                      0: self
                        10      LOAD_ATTR                       0: bank_select_windows
                        20      LOAD_METHOD                     1: destroy
                        42      PRECALL                         0
                        46      CALL                            0
                        56      POP_TOP                         
                        58      JUMP_FORWARD                    7 (to 74)
                        60      PUSH_EXC_INFO                   
                        62      POP_TOP                         
                        64      POP_EXCEPT                      
                        66      JUMP_FORWARD                    3 (to 74)
                        68      COPY                            3
                        70      POP_EXCEPT                      
                        72      RERAISE                         1
                        74      LOAD_GLOBAL                     5: NULL + Tk
                        86      PRECALL                         0
                        90      CALL                            0
                        100     LOAD_DEREF                      0: self
                        102     STORE_ATTR                      0: bank_select_windows
                        112     LOAD_DEREF                      0: self
                        114     LOAD_ATTR                       0: bank_select_windows
                        124     LOAD_METHOD                     3: title
                        146     LOAD_CONST                      1: 'انتخاب بانک'
                        148     PRECALL                         1
                        152     CALL                            1
                        162     POP_TOP                         
                        164     LOAD_DEREF                      0: self
                        166     LOAD_ATTR                       0: bank_select_windows
                        176     LOAD_METHOD                     4: resizable
                        198     LOAD_CONST                      2: False
                        200     LOAD_CONST                      2: False
                        202     PRECALL                         2
                        206     CALL                            2
                        216     POP_TOP                         
                        218     LOAD_GLOBAL                     10: Grid
                        230     LOAD_METHOD                     6: rowconfigure
                        252     LOAD_DEREF                      0: self
                        254     LOAD_ATTR                       0: bank_select_windows
                        264     LOAD_CONST                      3: 0
                        266     LOAD_CONST                      4: 1
                        268     KW_NAMES                        5: ('weight',)
                        270     PRECALL                         3
                        274     CALL                            3
                        284     POP_TOP                         
                        286     LOAD_GLOBAL                     10: Grid
                        298     LOAD_METHOD                     7: columnconfigure
                        320     LOAD_DEREF                      0: self
                        322     LOAD_ATTR                       0: bank_select_windows
                        332     LOAD_CONST                      3: 0
                        334     LOAD_CONST                      4: 1
                        336     KW_NAMES                        5: ('weight',)
                        338     PRECALL                         3
                        342     CALL                            3
                        352     POP_TOP                         
                        354     LOAD_DEREF                      0: self
                        356     LOAD_ATTR                       0: bank_select_windows
                        366     LOAD_METHOD                     8: protocol
                        388     LOAD_CONST                      6: 'WM_DELETE_WINDOW'
                        390     PRECALL                         1
                        394     CALL                            1
                        404     POP_TOP                         
                        406     LOAD_GLOBAL                     19: NULL + Treeview
                        418     LOAD_DEREF                      0: self
                        420     LOAD_ATTR                       0: bank_select_windows
                        430     LOAD_CONST                      7: 'selected_bank'
                        432     LOAD_CONST                      8: 'headings'
                        434     KW_NAMES                        9: ('columns', 'show')
                        436     PRECALL                         3
                        440     CALL                            3
                        450     LOAD_DEREF                      0: self
                        452     STORE_ATTR                      10: selected_bank
                        462     LOAD_DEREF                      0: self
                        464     LOAD_ATTR                       10: selected_bank
                        474     LOAD_METHOD                     11: heading
                        496     LOAD_CONST                      7: 'selected_bank'
                        498     LOAD_CONST                      10: 'بانک های انتخاب شده'
                        500     KW_NAMES                        11: ('text',)
                        502     PRECALL                         2
                        506     CALL                            2
                        516     POP_TOP                         
                        518     LOAD_DEREF                      0: self
                        520     LOAD_ATTR                       10: selected_bank
                        530     LOAD_METHOD                     12: column
                        552     LOAD_CONST                      7: 'selected_bank'
                        554     LOAD_CONST                      12: 'e'
                        556     KW_NAMES                        13: ('anchor',)
                        558     PRECALL                         2
                        562     CALL                            2
                        572     POP_TOP                         
                        574     LOAD_FAST                       3: selected_bank_list_
                        576     GET_ITER                        
                        578     FOR_ITER                        34 (to 648)
                        580     STORE_FAST                      5: i
                        582     LOAD_DEREF                      0: self
                        584     LOAD_ATTR                       10: selected_bank
                        594     LOAD_METHOD                     13: insert
                        616     LOAD_CONST                      14: ''
                        618     LOAD_CONST                      15: 'end'
                        620     LOAD_FAST                       5: i
                        622     LOAD_FAST                       5: i
                        624     LOAD_FAST                       5: i
                        626     BUILD_TUPLE                     1
                        628     KW_NAMES                        16: ('text', 'values')
                        630     PRECALL                         5
                        634     CALL                            5
                        644     POP_TOP                         
                        646     JUMP_BACKWARD                   35 (to 578)
                        648     LOAD_GLOBAL                     19: NULL + Treeview
                        660     LOAD_DEREF                      0: self
                        662     LOAD_ATTR                       0: bank_select_windows
                        672     LOAD_CONST                      17: 'bank_list'
                        674     LOAD_CONST                      8: 'headings'
                        676     KW_NAMES                        9: ('columns', 'show')
                        678     PRECALL                         3
                        682     CALL                            3
                        692     LOAD_DEREF                      0: self
                        694     STORE_ATTR                      14: unselected_bank
                        704     LOAD_DEREF                      0: self
                        706     LOAD_ATTR                       14: unselected_bank
                        716     LOAD_METHOD                     11: heading
                        738     LOAD_CONST                      17: 'bank_list'
                        740     LOAD_CONST                      18: 'لیست بانک ها'
                        742     KW_NAMES                        11: ('text',)
                        744     PRECALL                         2
                        748     CALL                            2
                        758     POP_TOP                         
                        760     LOAD_DEREF                      0: self
                        762     LOAD_ATTR                       14: unselected_bank
                        772     LOAD_METHOD                     12: column
                        794     LOAD_CONST                      17: 'bank_list'
                        796     LOAD_CONST                      12: 'e'
                        798     KW_NAMES                        13: ('anchor',)
                        800     PRECALL                         2
                        804     CALL                            2
                        814     POP_TOP                         
                        816     LOAD_FAST                       2: bank_list_
                        818     GET_ITER                        
                        820     FOR_ITER                        34 (to 890)
                        822     STORE_FAST                      5: i
                        824     LOAD_DEREF                      0: self
                        826     LOAD_ATTR                       14: unselected_bank
                        836     LOAD_METHOD                     13: insert
                        858     LOAD_CONST                      14: ''
                        860     LOAD_CONST                      15: 'end'
                        862     LOAD_FAST                       5: i
                        864     LOAD_FAST                       5: i
                        866     LOAD_FAST                       5: i
                        868     BUILD_TUPLE                     1
                        870     KW_NAMES                        16: ('text', 'values')
                        872     PRECALL                         5
                        876     CALL                            5
                        886     POP_TOP                         
                        888     JUMP_BACKWARD                   35 (to 820)
                        890     LOAD_DEREF                      0: self
                        892     LOAD_ATTR                       10: selected_bank
                        902     LOAD_METHOD                     15: grid
                        924     LOAD_CONST                      3: 0
                        926     LOAD_CONST                      3: 0
                        928     LOAD_CONST                      19: 'nsew'
                        930     LOAD_CONST                      20: 7
                        932     KW_NAMES                        21: ('column', 'row', 'sticky', 'padx')
                        934     PRECALL                         4
                        938     CALL                            4
                        948     POP_TOP                         
                        950     LOAD_DEREF                      0: self
                        952     LOAD_ATTR                       14: unselected_bank
                        962     LOAD_METHOD                     15: grid
                        984     LOAD_CONST                      22: 2
                        986     LOAD_CONST                      3: 0
                        988     LOAD_CONST                      19: 'nsew'
                        990     LOAD_CONST                      20: 7
                        992     KW_NAMES                        21: ('column', 'row', 'sticky', 'padx')
                        994     PRECALL                         4
                        998     CALL                            4
                        1008    POP_TOP                         
                        1010    LOAD_GLOBAL                     33: NULL + Button
                        1022    LOAD_DEREF                      0: self
                        1024    LOAD_ATTR                       0: bank_select_windows
                        1034    LOAD_CONST                      23: 'ذخیره'
                        1036    LOAD_CLOSURE                    4: mode
                        1038    LOAD_CLOSURE                    0: self
                        1040    BUILD_TUPLE                     2
                        1042    LOAD_CONST                      24: <CODE> <lambda>
                        1044    MAKE_FUNCTION                   8
                        1046    KW_NAMES                        25: ('text', 'command')
                        1048    PRECALL                         3
                        1052    CALL                            3
                        1062    LOAD_METHOD                     15: grid
                        1084    LOAD_CONST                      4: 1
                        1086    LOAD_CONST                      3: 0
                        1088    LOAD_CONST                      26: 4
                        1090    LOAD_CONST                      27: 'ew'
                        1092    LOAD_CONST                      28: 10
                        1094    LOAD_CONST                      28: 10
                        1096    KW_NAMES                        29: ('row', 'column', 'columnspan', 'sticky', 'pady', 'padx')
                        1098    PRECALL                         6
                        1102    CALL                            6
                        1112    POP_TOP                         
                        1114    LOAD_GLOBAL                     35: NULL + Scrollbar
                        1126    LOAD_DEREF                      0: self
                        1128    LOAD_ATTR                       0: bank_select_windows
                        1138    LOAD_GLOBAL                     36: VERTICAL
                        1150    LOAD_DEREF                      0: self
                        1152    LOAD_ATTR                       10: selected_bank
                        1162    LOAD_ATTR                       19: yview
                        1172    KW_NAMES                        30: ('orient', 'command')
                        1174    PRECALL                         3
                        1178    CALL                            3
                        1188    STORE_FAST                      6: scrollbar
                        1190    LOAD_DEREF                      0: self
                        1192    LOAD_ATTR                       10: selected_bank
                        1202    LOAD_METHOD                     20: configure
                        1224    LOAD_FAST                       6: scrollbar
                        1226    LOAD_ATTR                       21: set
                        1236    KW_NAMES                        31: ('yscroll',)
                        1238    PRECALL                         1
                        1242    CALL                            1
                        1252    POP_TOP                         
                        1254    LOAD_FAST                       6: scrollbar
                        1256    LOAD_METHOD                     15: grid
                        1278    LOAD_CONST                      3: 0
                        1280    LOAD_CONST                      4: 1
                        1282    LOAD_CONST                      32: 'ns'
                        1284    KW_NAMES                        33: ('row', 'column', 'sticky')
                        1286    PRECALL                         3
                        1290    CALL                            3
                        1300    POP_TOP                         
                        1302    LOAD_GLOBAL                     35: NULL + Scrollbar
                        1314    LOAD_DEREF                      0: self
                        1316    LOAD_ATTR                       0: bank_select_windows
                        1326    LOAD_GLOBAL                     36: VERTICAL
                        1338    LOAD_DEREF                      0: self
                        1340    LOAD_ATTR                       14: unselected_bank
                        1350    LOAD_ATTR                       19: yview
                        1360    KW_NAMES                        30: ('orient', 'command')
                        1362    PRECALL                         3
                        1366    CALL                            3
                        1376    STORE_FAST                      6: scrollbar
                        1378    LOAD_DEREF                      0: self
                        1380    LOAD_ATTR                       14: unselected_bank
                        1390    LOAD_METHOD                     20: configure
                        1412    LOAD_FAST                       6: scrollbar
                        1414    LOAD_ATTR                       21: set
                        1424    KW_NAMES                        31: ('yscroll',)
                        1426    PRECALL                         1
                        1430    CALL                            1
                        1440    POP_TOP                         
                        1442    LOAD_FAST                       6: scrollbar
                        1444    LOAD_METHOD                     15: grid
                        1466    LOAD_CONST                      3: 0
                        1468    LOAD_CONST                      34: 3
                        1470    LOAD_CONST                      32: 'ns'
                        1472    KW_NAMES                        33: ('row', 'column', 'sticky')
                        1474    PRECALL                         3
                        1478    CALL                            3
                        1488    POP_TOP                         
                        1490    LOAD_DEREF                      0: self
                        1492    LOAD_ATTR                       14: unselected_bank
                        1502    LOAD_METHOD                     22: bind
                        1524    LOAD_CONST                      35: '<<TreeviewSelect>>'
                        1526    LOAD_DEREF                      0: self
                        1528    LOAD_ATTR                       23: selectBank
                        1538    PRECALL                         2
                        1542    CALL                            2
                        1552    POP_TOP                         
                        1554    LOAD_DEREF                      0: self
                        1556    LOAD_ATTR                       10: selected_bank
                        1566    LOAD_METHOD                     22: bind
                        1588    LOAD_CONST                      35: '<<TreeviewSelect>>'
                        1590    LOAD_DEREF                      0: self
                        1592    LOAD_ATTR                       24: unselectBank
                        1602    PRECALL                         2
                        1606    CALL                            2
                        1616    POP_TOP                         
                        1618    LOAD_DEREF                      0: self
                        1620    LOAD_ATTR                       0: bank_select_windows
                        1630    LOAD_METHOD                     25: mainloop
                        1652    PRECALL                         0
                        1656    CALL                            0
                        1666    POP_TOP                         
                        1668    LOAD_CONST                      0: None
                        1670    RETURN_VALUE                    
                [Code]
                    File Name: jetvam.pyw
                    Object Name: closeDialogBank
                    Qualified Name: MyApp.closeDialogBank
                    Arg Count: 2
                    Pos Only Arg Count: 0
                    KW Only Arg Count: 0
                    Stack Size: 6
                    Flags: 0x00000003 (CO_OPTIMIZED | CO_NEWLOCALS)
                    [Names]
                        'selected_bank'
                        'get_children'
                        'selected_bank_list'
                        'list'
                        'unselected_bank'
                        'unselected_bank_list'
                        'entry_bank_entekhabi'
                        'delete'
                        'END'
                        'insert'
                        'join'
                        'selected_bank_list_alarm'
                        'unselected_bank_list_alarm'
                        'entry_alarm_bank'
                        'bank_select_windows'
                        'destroy'
                    [Locals+Names]
                        'self'
                        'mode'
                    [Constants]
                        None
                        'select'
                        0
                        ', '
                    [Disassembly]
                        0       RESUME                          0
                        2       LOAD_FAST                       1: mode
                        4       LOAD_CONST                      1: 'select'
                        6       COMPARE_OP                      2 (==)
                        12      POP_JUMP_FORWARD_IF_FALSE       157 (to 328)
                        14      LOAD_FAST                       0: self
                        16      LOAD_ATTR                       0: selected_bank
                        26      LOAD_METHOD                     1: get_children
                        48      PRECALL                         0
                        52      CALL                            0
                        62      LOAD_FAST                       0: self
                        64      STORE_ATTR                      2: selected_bank_list
                        74      LOAD_GLOBAL                     7: NULL + list
                        86      LOAD_FAST                       0: self
                        88      LOAD_ATTR                       4: unselected_bank
                        98      LOAD_METHOD                     1: get_children
                        120     PRECALL                         0
                        124     CALL                            0
                        134     PRECALL                         1
                        138     CALL                            1
                        148     LOAD_FAST                       0: self
                        150     STORE_ATTR                      5: unselected_bank_list
                        160     LOAD_FAST                       0: self
                        162     LOAD_ATTR                       6: entry_bank_entekhabi
                        172     LOAD_METHOD                     7: delete
                        194     LOAD_CONST                      2: 0
                        196     LOAD_GLOBAL                     16: END
                        208     PRECALL                         2
                        212     CALL                            2
                        222     POP_TOP                         
                        224     LOAD_FAST                       0: self
                        226     LOAD_ATTR                       6: entry_bank_entekhabi
                        236     LOAD_METHOD                     9: insert
                        258     LOAD_CONST                      2: 0
                        260     LOAD_CONST                      3: ', '
                        262     LOAD_METHOD                     10: join
                        284     LOAD_FAST                       0: self
                        286     LOAD_ATTR                       2: selected_bank_list
                        296     PRECALL                         1
                        300     CALL                            1
                        310     PRECALL                         2
                        314     CALL                            2
                        324     POP_TOP                         
                        326     JUMP_FORWARD                    156 (to 640)
                        328     LOAD_FAST                       0: self
                        330     LOAD_ATTR                       0: selected_bank
                        340     LOAD_METHOD                     1: get_children
                        362     PRECALL                         0
                        366     CALL                            0
                        376     LOAD_FAST                       0: self
                        378     STORE_ATTR                      11: selected_bank_list_alarm
                        388     LOAD_GLOBAL                     7: NULL + list
                        400     LOAD_FAST                       0: self
                        402     LOAD_ATTR                       4: unselected_bank
                        412     LOAD_METHOD                     1: get_children
                        434     PRECALL                         0
                        438     CALL                            0
                        448     PRECALL                         1
                        452     CALL                            1
                        462     LOAD_FAST                       0: self
                        464     STORE_ATTR                      12: unselected_bank_list_alarm
                        474     LOAD_FAST                       0: self
                        476     LOAD_ATTR                       13: entry_alarm_bank
                        486     LOAD_METHOD                     7: delete
                        508     LOAD_CONST                      2: 0
                        510     LOAD_GLOBAL                     16: END
                        522     PRECALL                         2
                        526     CALL                            2
                        536     POP_TOP                         
                        538     LOAD_FAST                       0: self
                        540     LOAD_ATTR                       13: entry_alarm_bank
                        550     LOAD_METHOD                     9: insert
                        572     LOAD_CONST                      2: 0
                        574     LOAD_CONST                      3: ', '
                        576     LOAD_METHOD                     10: join
                        598     LOAD_FAST                       0: self
                        600     LOAD_ATTR                       11: selected_bank_list_alarm
                        610     PRECALL                         1
                        614     CALL                            1
                        624     PRECALL                         2
                        628     CALL                            2
                        638     POP_TOP                         
                        640     LOAD_FAST                       0: self
                        642     LOAD_ATTR                       14: bank_select_windows
                        652     LOAD_METHOD                     15: destroy
                        674     PRECALL                         0
                        678     CALL                            0
                        688     POP_TOP                         
                        690     LOAD_CONST                      0: None
                        692     RETURN_VALUE                    
                [Code]
                    File Name: jetvam.pyw
                    Object Name: selectBank
                    Qualified Name: MyApp.selectBank
                    Arg Count: 2
                    Pos Only Arg Count: 0
                    KW Only Arg Count: 0
                    Stack Size: 8
                    Flags: 0x00000003 (CO_OPTIMIZED | CO_NEWLOCALS)
                    [Names]
                        'unselected_bank'
                        'selection'
                        'item'
                        'selected_bank'
                        'insert'
                        'delete'
                    [Locals+Names]
                        'self'
                        'event'
                        'selected_item'
                        'item'
                        'record'
                    [Constants]
                        None
                        'values'
                        0
                        ''
                        'end'
                        (
                            'text'
                            'values'
                        )
                    [Disassembly]
                        0       RESUME                          0
                        2       LOAD_FAST                       0: self
                        4       LOAD_ATTR                       0: unselected_bank
                        14      LOAD_METHOD                     1: selection
                        36      PRECALL                         0
                        40      CALL                            0
                        50      GET_ITER                        
                        52      FOR_ITER                        100 (to 254)
                        54      STORE_FAST                      2: selected_item
                        56      LOAD_FAST                       0: self
                        58      LOAD_ATTR                       0: unselected_bank
                        68      LOAD_METHOD                     2: item
                        90      LOAD_FAST                       2: selected_item
                        92      PRECALL                         1
                        96      CALL                            1
                        106     STORE_FAST                      3: item
                        108     LOAD_FAST                       3: item
                        110     LOAD_CONST                      1: 'values'
                        112     BINARY_SUBSCR                   
                        122     LOAD_CONST                      2: 0
                        124     BINARY_SUBSCR                   
                        134     STORE_FAST                      4: record
                        136     LOAD_FAST                       0: self
                        138     LOAD_ATTR                       3: selected_bank
                        148     LOAD_METHOD                     4: insert
                        170     LOAD_CONST                      3: ''
                        172     LOAD_CONST                      4: 'end'
                        174     LOAD_FAST                       4: record
                        176     LOAD_FAST                       4: record
                        178     LOAD_FAST                       4: record
                        180     BUILD_TUPLE                     1
                        182     KW_NAMES                        5: ('text', 'values')
                        184     PRECALL                         5
                        188     CALL                            5
                        198     POP_TOP                         
                        200     LOAD_FAST                       0: self
                        202     LOAD_ATTR                       0: unselected_bank
                        212     LOAD_METHOD                     5: delete
                        234     LOAD_FAST                       4: record
                        236     PRECALL                         1
                        240     CALL                            1
                        250     POP_TOP                         
                        252     JUMP_BACKWARD                   101 (to 52)
                        254     LOAD_CONST                      0: None
                        256     RETURN_VALUE                    
                [Code]
                    File Name: jetvam.pyw
                    Object Name: unselectBank
                    Qualified Name: MyApp.unselectBank
                    Arg Count: 2
                    Pos Only Arg Count: 0
                    KW Only Arg Count: 0
                    Stack Size: 8
                    Flags: 0x00000003 (CO_OPTIMIZED | CO_NEWLOCALS)
                    [Names]
                        'selected_bank'
                        'selection'
                        'item'
                        'unselected_bank'
                        'insert'
                        'delete'
                    [Locals+Names]
                        'self'
                        'event'
                        'selected_item'
                        'item'
                        'record'
                    [Constants]
                        None
                        'values'
                        0
                        ''
                        'end'
                        (
                            'text'
                            'values'
                        )
                    [Disassembly]
                        0       RESUME                          0
                        2       LOAD_FAST                       0: self
                        4       LOAD_ATTR                       0: selected_bank
                        14      LOAD_METHOD                     1: selection
                        36      PRECALL                         0
                        40      CALL                            0
                        50      GET_ITER                        
                        52      FOR_ITER                        100 (to 254)
                        54      STORE_FAST                      2: selected_item
                        56      LOAD_FAST                       0: self
                        58      LOAD_ATTR                       0: selected_bank
                        68      LOAD_METHOD                     2: item
                        90      LOAD_FAST                       2: selected_item
                        92      PRECALL                         1
                        96      CALL                            1
                        106     STORE_FAST                      3: item
                        108     LOAD_FAST                       3: item
                        110     LOAD_CONST                      1: 'values'
                        112     BINARY_SUBSCR                   
                        122     LOAD_CONST                      2: 0
                        124     BINARY_SUBSCR                   
                        134     STORE_FAST                      4: record
                        136     LOAD_FAST                       0: self
                        138     LOAD_ATTR                       3: unselected_bank
                        148     LOAD_METHOD                     4: insert
                        170     LOAD_CONST                      3: ''
                        172     LOAD_CONST                      4: 'end'
                        174     LOAD_FAST                       4: record
                        176     LOAD_FAST                       4: record
                        178     LOAD_FAST                       4: record
                        180     BUILD_TUPLE                     1
                        182     KW_NAMES                        5: ('text', 'values')
                        184     PRECALL                         5
                        188     CALL                            5
                        198     POP_TOP                         
                        200     LOAD_FAST                       0: self
                        202     LOAD_ATTR                       0: selected_bank
                        212     LOAD_METHOD                     5: delete
                        234     LOAD_FAST                       4: record
                        236     PRECALL                         1
                        240     CALL                            1
                        250     POP_TOP                         
                        252     JUMP_BACKWARD                   101 (to 52)
                        254     LOAD_CONST                      0: None
                        256     RETURN_VALUE                    
                [Code]
                    File Name: jetvam.pyw
                    Object Name: changeCaptchaAutomat
                    Qualified Name: MyApp.changeCaptchaAutomat
                    Arg Count: 1
                    Pos Only Arg Count: 0
                    KW Only Arg Count: 0
                    Stack Size: 3
                    Flags: 0x00000003 (CO_OPTIMIZED | CO_NEWLOCALS)
                    [Names]
                        'check_captcha_automat'
                        'state'
                        'automation'
                        'sabt_capcha_pending'
                        'button_sabt_captcha'
                        'config'
                        'entry_captcha'
                    [Locals+Names]
                        'self'
                        'state'
                    [Constants]
                        None
                        'selected'
                        True
                        False
                        'disabled'
                        'normal'
                        (
                            'state'
                        )
                    [Disassembly]
                        0       RESUME                          0
                        2       LOAD_CONST                      1: 'selected'
                        4       LOAD_FAST                       0: self
                        6       LOAD_ATTR                       0: check_captcha_automat
                        16      LOAD_METHOD                     1: state
                        38      PRECALL                         0
                        42      CALL                            0
                        52      CONTAINS_OP                     0 (in)
                        54      STORE_FAST                      1: state
                        56      LOAD_FAST                       1: state
                        58      LOAD_CONST                      2: True
                        60      COMPARE_OP                      2 (==)
                        66      POP_JUMP_FORWARD_IF_FALSE       12 (to 92)
                        68      LOAD_CONST                      3: False
                        70      LOAD_FAST                       0: self
                        72      LOAD_ATTR                       2: automation
                        82      STORE_ATTR                      3: sabt_capcha_pending
                        92      LOAD_FAST                       0: self
                        94      LOAD_ATTR                       4: button_sabt_captcha
                        104     LOAD_METHOD                     5: config
                        126     LOAD_FAST                       1: state
                        128     POP_JUMP_FORWARD_IF_FALSE       2 (to 134)
                        130     LOAD_CONST                      4: 'disabled'
                        132     JUMP_FORWARD                    1 (to 136)
                        134     LOAD_CONST                      5: 'normal'
                        136     KW_NAMES                        6: ('state',)
                        138     PRECALL                         1
                        142     CALL                            1
                        152     POP_TOP                         
                        154     LOAD_FAST                       0: self
                        156     LOAD_ATTR                       6: entry_captcha
                        166     LOAD_METHOD                     5: config
                        188     LOAD_FAST                       1: state
                        190     POP_JUMP_FORWARD_IF_FALSE       2 (to 196)
                        192     LOAD_CONST                      4: 'disabled'
                        194     JUMP_FORWARD                    1 (to 198)
                        196     LOAD_CONST                      5: 'normal'
                        198     KW_NAMES                        6: ('state',)
                        200     PRECALL                         1
                        204     CALL                            1
                        214     POP_TOP                         
                        216     LOAD_CONST                      0: None
                        218     RETURN_VALUE                    
                [Code]
                    File Name: jetvam.pyw
                    Object Name: showSupport
                    Qualified Name: MyApp.showSupport
                    Arg Count: 1
                    Pos Only Arg Count: 0
                    KW Only Arg Count: 0
                    Stack Size: 6
                    Flags: 0x00000003 (CO_OPTIMIZED | CO_NEWLOCALS)
                    [Names]
                        'support_window'
                        'destroy'
                        'Tk'
                        'resizable'
                        'title'
                        'Label'
                        'grid'
                        'app_version'
                        'mainloop'
                    [Locals+Names]
                        'self'
                        'window'
                    [Constants]
                        None
                        False
                        'پشتیبانی'
                        'آیدی تلگرام'
                        (
                            'text'
                        )
                        1
                        40
                        20
                        (
                            'row'
                            'column'
                            'padx'
                            'pady'
                        )
                        '@jetvamezdevaj'
                        0
                        'نسخه نرم افزار'
                        2
                    [Disassembly]
                        0       RESUME                          0
                        2       NOP                             
                        4       LOAD_FAST                       0: self
                        6       LOAD_ATTR                       0: support_window
                        16      LOAD_METHOD                     1: destroy
                        38      PRECALL                         0
                        42      CALL                            0
                        52      POP_TOP                         
                        54      JUMP_FORWARD                    7 (to 70)
                        56      PUSH_EXC_INFO                   
                        58      POP_TOP                         
                        60      POP_EXCEPT                      
                        62      JUMP_FORWARD                    3 (to 70)
                        64      COPY                            3
                        66      POP_EXCEPT                      
                        68      RERAISE                         1
                        70      LOAD_GLOBAL                     5: NULL + Tk
                        82      PRECALL                         0
                        86      CALL                            0
                        96      LOAD_FAST                       0: self
                        98      STORE_ATTR                      0: support_window
                        108     LOAD_FAST                       0: self
                        110     LOAD_ATTR                       0: support_window
                        120     STORE_FAST                      1: window
                        122     LOAD_FAST                       1: window
                        124     LOAD_METHOD                     3: resizable
                        146     LOAD_CONST                      1: False
                        148     LOAD_CONST                      1: False
                        150     PRECALL                         2
                        154     CALL                            2
                        164     POP_TOP                         
                        166     LOAD_FAST                       1: window
                        168     LOAD_METHOD                     4: title
                        190     LOAD_CONST                      2: 'پشتیبانی'
                        192     PRECALL                         1
                        196     CALL                            1
                        206     POP_TOP                         
                        208     LOAD_GLOBAL                     11: NULL + Label
                        220     LOAD_FAST                       1: window
                        222     LOAD_CONST                      3: 'آیدی تلگرام'
                        224     KW_NAMES                        4: ('text',)
                        226     PRECALL                         2
                        230     CALL                            2
                        240     LOAD_METHOD                     6: grid
                        262     LOAD_CONST                      5: 1
                        264     LOAD_CONST                      5: 1
                        266     LOAD_CONST                      6: 40
                        268     LOAD_CONST                      7: 20
                        270     KW_NAMES                        8: ('row', 'column', 'padx', 'pady')
                        272     PRECALL                         4
                        276     CALL                            4
                        286     POP_TOP                         
                        288     LOAD_GLOBAL                     11: NULL + Label
                        300     LOAD_FAST                       1: window
                        302     LOAD_CONST                      9: '@jetvamezdevaj'
                        304     KW_NAMES                        4: ('text',)
                        306     PRECALL                         2
                        310     CALL                            2
                        320     LOAD_METHOD                     6: grid
                        342     LOAD_CONST                      5: 1
                        344     LOAD_CONST                      10: 0
                        346     LOAD_CONST                      6: 40
                        348     LOAD_CONST                      7: 20
                        350     KW_NAMES                        8: ('row', 'column', 'padx', 'pady')
                        352     PRECALL                         4
                        356     CALL                            4
                        366     POP_TOP                         
                        368     LOAD_GLOBAL                     11: NULL + Label
                        380     LOAD_FAST                       1: window
                        382     LOAD_CONST                      11: 'نسخه نرم افزار'
                        384     KW_NAMES                        4: ('text',)
                        386     PRECALL                         2
                        390     CALL                            2
                        400     LOAD_METHOD                     6: grid
                        422     LOAD_CONST                      12: 2
                        424     LOAD_CONST                      5: 1
                        426     LOAD_CONST                      6: 40
                        428     LOAD_CONST                      7: 20
                        430     KW_NAMES                        8: ('row', 'column', 'padx', 'pady')
                        432     PRECALL                         4
                        436     CALL                            4
                        446     POP_TOP                         
                        448     LOAD_GLOBAL                     11: NULL + Label
                        460     LOAD_FAST                       1: window
                        462     LOAD_GLOBAL                     14: app_version
                        474     KW_NAMES                        4: ('text',)
                        476     PRECALL                         2
                        480     CALL                            2
                        490     LOAD_METHOD                     6: grid
                        512     LOAD_CONST                      12: 2
                        514     LOAD_CONST                      10: 0
                        516     LOAD_CONST                      6: 40
                        518     LOAD_CONST                      7: 20
                        520     KW_NAMES                        8: ('row', 'column', 'padx', 'pady')
                        522     PRECALL                         4
                        526     CALL                            4
                        536     POP_TOP                         
                        538     LOAD_FAST                       1: window
                        540     LOAD_METHOD                     8: mainloop
                        562     PRECALL                         0
                        566     CALL                            0
                        576     POP_TOP                         
                        578     LOAD_CONST                      0: None
                        580     RETURN_VALUE                    
                [Code]
                    File Name: jetvam.pyw
                    Object Name: showSettings
                    Qualified Name: MyApp.showSettings
                    Arg Count: 1
                    Pos Only Arg Count: 0
                    KW Only Arg Count: 0
                    Stack Size: 60
                    Flags: 0x00000003 (CO_OPTIMIZED | CO_NEWLOCALS)
                    [Names]
                        'is_show_setting_windos'
                        'settings_window'
                        'destroy'
                        'Tk'
                        'config'
                        'resizable'
                        'geometry'
                        'title'
                        'Style'
                        'configure'
                        'Notebook'
                        'Frame'
                        'add'
                        'jbdb_license'
                        'Grid'
                        'columnconfigure'
                        'select'
                        'grid'
                        'Checkbutton'
                        'state'
                        'settings'
                        'default_padx'
                        'default_pady'
                        'Labelframe'
                        'Label'
                        'Entry'
                        'register'
                        'validate'
                        'insert'
                        'ToolTip'
                        'Button'
                        'os_platform'
                        'bind'
                        'RightClicker'
                        'Text'
                        'text_sms'
                        'tag_config'
                        'END'
                        'proxy_list'
                        'int'
                        'until_time'
                        'globals'
                        'jbdb_until_time'
                        'Font'
                        'master'
                        'BOLD'
                        'tkinter_Button'
                        'activeAutoStartFeature'
                        'showRestoreMember'
                        'dns_val'
                        'IntVar'
                        'Radiobutton'
                        'invoke'
                        'check_refresh_time_milisec'
                        'check_captcha_automat'
                        'sabte_khodkar'
                        'auto_start_check'
                        'auto_start_check_along_all'
                        'auto_active_captcha_solver_check'
                        'check_get_new_code_secondry_province_auto_timer'
                        'check_temporary_auto_sms'
                        'auto_active_auto_commit_member_check'
                        'check_buttons_list'
                        'check_buttons_state_list'
                        'protocol'
                        'mainloop'
                    [Locals+Names]
                        'self'
                        'style'
                        'tab_controll'
                        'settings_tab1'
                        'settings_tab2'
                        'settings_tab3'
                        'settings_tab4'
                        'settings_tab5'
                        'settings_tab6'
                        'frame_refresh'
                        'frame_work_time'
                        'frame_commit'
                        'frame_change_bank_in_budjet_mode'
                        'tooltip_message'
                        'frame_safe_settings_parent'
                        'frame_safe_settings'
                        'entry_meli_sms'
                        'frame_proxy'
                        'day_expire'
                        'hour_expire'
                        'frame_license'
                        'font_bold8'
                        'frame_database'
                        'frame_debug'
                        'frame_sms'
                        'frame_secure_dns'
                        'frame_secure_dns_radio_btns'
                        'int_var_dns'
                        'r1'
                        'r2'
                        'r3'
                        'r4'
                        'changeDnsVal'
                        'check_auto_sms'
                        'check_change_bank_in_budjet_mode'
                        'check_debug_is_on'
                        'check_force_close_wait_error'
                        'check_namayesh_after_seconds_error'
                        'check_namayesh_page_one_step_two'
                        'check_namayesh_page_two'
                        'check_namayesh_page_two_auto_start'
                        'check_namayesh_restart'
                        'check_namayesh_unrecognize_captcha'
                        'check_nemayesh_notif_bank'
                        'check_nemayesh_notif_save'
                        'check_nemayesh_notif_select_bank'
                        'check_next_user'
                        'check_other_bank'
                        'check_proxy_change_after_commit_member'
                        'check_proxy_change_page_one'
                        'check_proxy_change_page_two'
                        'check_proxy_extention_mode'
                        'check_refresh_captcha_before_commit_member'
                        'check_refresh_expire_sms_code'
                        'check_refresh_form_restart'
                        'check_safe_change_list_order'
                        'check_safe_change_same_bank'
                        'check_safe_change_same_city'
                        'check_safe_change_same_province'
                        'check_safe_run'
                        'check_seda_notif_after_seconds_error'
                        'check_seda_notif_bank'
                        'check_seda_notif_page_one_step_two'
                        'check_seda_notif_page_two'
                        'check_seda_notif_page_two_auto_start'
                        'check_seda_notif_restart'
                        'check_seda_notif_save'
                        'check_seda_notif_select_bank'
                        'check_seda_notif_unrecognize_captcha'
                        'check_stop_auto_captcha_solver_in_page_three'
                        'check_uc_local'
                        'check_wait_for_sms_before_commit'
                        'disableChildren'
                        'enableChildren'
                        'entry_bank_count'
                        'entry_bank_time'
                        'entry_captcha_time'
                        'entry_captcha_time_2'
                        'entry_captcha_time_page_one_step_two'
                        'entry_captcha_time_unrecognize'
                        'entry_commit_wait_time'
                        'entry_form_time'
                        'entry_form_time_page_midle'
                        'entry_proxy_chage_time'
                        'entry_safe_change_time'
                        'entry_start_h'
                        'entry_start_m'
                        'entry_stop_h'
                        'entry_stop_m'
                        'window'
                    [Constants]
                        None
                        True
                        '#F0F0F0'
                        (
                            'background'
                        )
                        False
                        '+0+0'
                        'تنظیمات'
                        'righttab.TNotebook'
                        'ne'
                        (
                            'tabposition'
                            'background'
                        )
                        20
                        (
                            'style'
                            'padding'
                        )
                        'بیشتر'
                        'nsew'
                        10
                        (
                            'text'
                            'sticky'
                            'padding'
                        )
                        'پروکسی'
                        'sms forwarder'
                        'اتوماسیون (۲)'
                        'اتوماسیون (۱)'
                        'اعلان'
                        0
                        1
                        (
                            'weight'
                        )
                        3
                        'nesw'
                        (
                            'row'
                            'rowspan'
                            'sticky'
                        )
                        'نمایش اعلان در صورت وجود بانک مورد نظر'
                        (
                            'text'
                        )
                        't1c1'
                        '!alternate'
                        'selected'
                        'پخش صدای اعلان در صورت وجود بانک مورد نظر'
                        't1c2'
                        'نمایش اعلان در صورت وجود بانک آلارم'
                        't1c3'
                        'پخش صدای اعلان در صورت وجود بانک آلارم'
                        't1c4'
                        'نمایش اعلان در صورت ثبت شدن کاربر'
                        't1c5'
                        'پخش صدای اعلان در صورت ثبت کاربر'
                        't1c6'
                        'نمایش اعلان در صورت مشاهده کپچای نا شناخته'
                        't1c7'
                        'پخش صدای اعلان در صورت مشاهده کپچای نا شناخته'
                        't1c8'
                        'نمایش اعلان در صورت شروع مجدد'
                        't1c9'
                        'پخش صدای اعلان در صورت شروع مجدد'
                        't1c10'
                        'نمایش اعلان در صورت خطای پس از چند ثانیه'
                        't1c11'
                        'پخش صدای اعلان در صورت خطای پس از چند ثانیه'
                        't1c12'
                        'نمایش اعلان در هنگام ورود به صفحه دوم'
                        't1c17'
                        'پخش صدای اعلان در هنگام ورود به صفحه دوم'
                        't1c18'
                        'نمایش اعلان در هنگام ورود به صفحه سوم'
                        't1c13'
                        'پخش صدای اعلان در هنگام ورود به صفحه سوم'
                        't1c14'
                        'نمایش اعلان در هنگام ورود به صفحه سوم (جنوک)'
                        't1c15'
                        'پخش صدای اعلان در هنگام ورود به صفحه سوم (جنوک)'
                        't1c16'
                        2
                        'e'
                        (
                            'row'
                            'column'
                            'padx'
                            'pady'
                            'sticky'
                        )
                        4
                        5
                        6
                        7
                        8
                        9
                        11
                        12
                        13
                        14
                        15
                        16
                        17
                        'نرخ رفرش'
                        (
                            'text'
                            'labelanchor'
                        )
                        'رفرش کپچا صفحه اول (ثانیه)'
                        'key'
                        '%P'
                        'int'
                        (
                            'width'
                            'validate'
                            'validatecommand'
                        )
                        't2e1'
                        'رفرش کپچا صفحه دوم (ثانیه)'
                        't2e10'
                        'رفرش کپچا ثبت نهایی (ثانیه)'
                        't2e1p2'
                        'چک کردن بانک (ثانیه)'
                        't2e3'
                        'رفرش کپچا ناشناخته (ثانیه)'
                        't2e1p3'
                        'رفرش فرم صفحه دوم (ثانیه)'
                        't2e11'
                        'رفرش کلی فرم (ثانیه)'
                        't2e2'
                        'ریست تایمر رفرش کلی فرم، لحظه ورود به صفحه سوم'
                        't2c4'
                        (
                            'columnspan'
                            'row'
                            'column'
                            'padx'
                            'pady'
                            'sticky'
                        )
                        (
                            'row'
                            'column'
                            'columnspan'
                            'padx'
                            'pady'
                            'sticky'
                        )
                        'زمان کار نرم افزار'
                        'ساعت شروع کار'
                        (
                            'column'
                            'row'
                            'padx'
                            'pady'
                            'sticky'
                        )
                        't2e5'
                        ':'
                        't2e4'
                        'ساعت اتمام کار'
                        't2e7'
                        't2e6'
                        'ثبت نهایی کاربر'
                        'زمان انتظار بعد از انتخاب بانک و قبل ثبت'
                        'تا تغییر نکردن کد پیامک ثبت فشرده نشود'
                        ''
                        't2e9'
                        't2c5'
                        'بعد از ثبت نام کاربر، کاربر بعدی را انتخاب کن'
                        't2c1'
                        'اگربانک انتخاب شده موجود نبود ولی بانک \nکاربر دیگر فعال بود، کاربر دیگر را ثبت نام کن'
                        't2c2'
                        'تعداد تلاش بعد از اتمام بودجه'
                        't2e8'
                        'تعویض بانک در حالت خطای بودجه'
                        (
                            'row'
                            'column'
                            'sticky'
                        )
                        't2c6'
                        'disabled'
                        'برای فعال سازی نیاز به سرویس پلاس هست'
                        0.05
                        '"بستن اجباری خطای "درحال بارگذاری'
                        't2c7'
                        'رفرش فرم در صورت اشتباه بودن یا منقضی شدن کد پیامک'
                        'توجه کنید تنظیمات برای انتظار تا دریافت کد جدید فعال باشد'
                        0.1
                        't2c8'
                        'توقف حل خودکار کپچا در صورت نبودن بانک مورد نظر'
                        't2c9'
                        'بعد از انتخاب شعبه ابتدا کپچا رفرش و سپس متقاضی ثبت شود'
                        't2c10'
                        'نصب دوباره درایور'
                        'شروع'
                        [Code]
                            File Name: jetvam.pyw
                            Object Name: <lambda>
                            Qualified Name: MyApp.showSettings.<locals>.<lambda>
                            Arg Count: 0
                            Pos Only Arg Count: 0
                            KW Only Arg Count: 0
                            Stack Size: 4
                            Flags: 0x00000013 (CO_OPTIMIZED | CO_NEWLOCALS | CO_NESTED)
                            [Names]
                                'showDownloadDriver'
                                'download_driver_message'
                            [Locals+Names]
                                'self'
                            [Constants]
                                None
                            [Disassembly]
                                0       COPY_FREE_VARS                  1
                                2       RESUME                          0
                                4       LOAD_GLOBAL                     1: NULL + showDownloadDriver
                                16      LOAD_GLOBAL                     2: download_driver_message
                                28      LOAD_DEREF                      0: self
                                30      PRECALL                         2
                                34      CALL                            2
                                44      RETURN_VALUE                    
                        (
                            'width'
                            'text'
                            'command'
                        )
                        'سرویس کپچای نا شناخته'
                        'سیستمی'
                        (
                            'width'
                            'text'
                        )
                        'win64'
                        't2c3'
                        'سرویس سیستمی به دلیل اجرا در همین سیستم، قطعی ندارد همچنین می تواند سرعت بهتری داشته باشد. قبل از استفاده از این سرویس باید نرم افزار مورد نیاز نصب شود. بعد از فعال سازی این قسمت و تایید تنظیمات در صورتی که نرم افزار نصب نشده باشد پیامی مبنی بر نصب ظاهر می شود که می توانید با استفاده از این دکمه اقدام به نصب این سرویس کنید'
                        'در حال حاضر این سرویس برای سیستم های 32 بیتی در دسترس نمی باشد'
                        'پیمایش امن'
                        't2p2c1'
                        'با فعال کردن این قابلیت، رفرش کردن صفحه تا زمانی که بانک مورد نظر یافت شود به تعویق می‌افتد و با این روش از بسته شدن دسترسی شما توسط بانک جلوگیری می‌شود، لازم به ذکر است اگر زمان پیدا شدن بانک کمتر از زمان رفرش باشد لازم به رفرش کردن صفحه نیست و متقاضی مستقیما ثبت می‌شود'
                        'تعویض کاربر'
                        'زمان مبنا'
                        't2p2e1'
                        'اگر در این مدت وارد صفحه اصلی ثبت نام نشد، کاربر را بر اساس تیک های موجود تغیر داده و سپس دوباره اتوماسیون اجرا می‌شود (تنظیم مقدار ۰ برای غیر فعال کردن) - لازم به ذکر است در صورت غیر فعال بودن تمامی تیک های پایین، قابلیت تعویض کاربر خاموش می‌شود. برای جلوگیری می‌توانید تیک "به ترتیب لیست" را همیشه روشن بگذارید'
                        'استان مشترک'
                        'شهر مشترک'
                        'بانک مشترک'
                        'به ترتیب لیست'
                        't2p2c2'
                        't2p2c3'
                        't2p2c4'
                        't2p2c5'
                        'درصورت وجود استان مشترک بین کاربر فعلی و کاربر دیگر، کاربر مورد نظر اولویت  داده می‌شود'
                        'در صورت وجود شهر مشترک بین کاربر فعلی و کاربر دیگر، کاربر مورد نظر اولویت داده می‌شود'
                        'درصورت وجود بانکی مشترک بین کاربر فعلی و کاربر دیگر، کاربر مورد نظر اولویت داده می‌شود'
                        'اگر موارد دیگر برای اولویت دادن وجود نداشت، به ترتیب، لیست متقاضیان انتخاب و اتوماسیون اجرا می‌شود. پیشنهاد می‌شود، این مورد همیشه روشن باشد'
                        'شماره موبایل'
                        (
                            'validate'
                            'validatecommand'
                        )
                        '<Button-3>'
                        'normal'
                        30
                        (
                            'background'
                            'state'
                            'width'
                        )
                        'tag-right'
                        'right'
                        (
                            'justify'
                        )
                        'لطفا شماره موبایل را به صورت کامل وارد کنید تا تنظیمات نمایان شود'
                        (
                            'state'
                        )
                        (
                            'row'
                            'column'
                            'columnspan'
                        )
                        'زمان تعویض (۰=خاموش)'
                        (
                            'validate'
                            'width'
                            'validatecommand'
                        )
                        'w'
                        'حالت افزونه'
                        't6c1'
                        'زمان فعال بودن (افزونه)'
                        'صفحات ورود'
                        't6c2'
                        'صفحه انتخاب بانک'
                        't6c3'
                        'بعد از ثبت هر متقاضی، پراکسی تعویض شود'
                        't6c4'
                        'برای فعال سازی این قابلیت نیاز به لایسنس پلاس دارید'
                        'هر پراکسی را در یک خط قرار دهید\nدر صورتی که پروکسی شما دارای\nیوزرنیم و پسورد هست، می‌توانید\nبعد از آدرس یک فاصله و بعد\nیوزرنیم و یک فاصله و پسورد را بنویسید\nبرای مثال به نمونه های زیر توجه کنید\n\n9.9.9.9:80\n10.10.10.10:443\n0.0.0.0:8080\n1.2.3.4:5679\n127.0.0.1:5060 username password\n\nتوجه کنید این تنظیمات بر روی\nسیستم شما اعمال می‌گردد\n\nدر صورت استفاده از افزونه پراکسی\nلازم است بعد از آدرس پراکسی یک فاصله\nو سپس نوع پراکسی مشخص شود برای مثال\n\n192.168.1.1:1020 http\n192.168.1.1:8080 socks5'
                        'زمان مبنا برای تعویض پراکسی\nبرای غیر فعال کردن 0 قرار دهید\n\nاین زمان تنها برای حالت سیستمی\n در نظر گرفته می‌شود\n\nدر صورت انتخاب حالت افزونه\nزمان تعویض به صورت\n خودکار تنظیم می‌شود'
                        't6e1'
                        't6e2'
                        86400
                        3600
                        'لایسنس نرم افزار'
                        ': انقضا'
                        (
                            'text'
                            'justify'
                        )
                        'تا پایان '
                        ' روز و '
                        ' ساعت مانده است'
                        'center'
                        'لایسنس پلاس'
                        'jbdb_until_time'
                        'سرویس پلاس برای شما فعال نمی‌باشد'
                        (
                            'size'
                            'weight'
                        )
                        'برای فعال سازی پلاس کلیک کنید'
                        '#0099FF'
                        'white'
                        (
                            'text'
                            'command'
                            'background'
                            'foreground'
                            'font'
                        )
                        (
                            'column'
                            'row'
                            'sticky'
                            'padx'
                            'pady'
                            'ipadx'
                        )
                        21
                        'دیتابیس'
                        'بازیابی کاربر پاک شده'
                        'بازیابی'
                        (
                            'text'
                            'command'
                        )
                        (
                            'row'
                            'padx'
                            'pady'
                            'sticky'
                        )
                        'دیباگ'
                        18
                        'برای فعال کردن دیباگ روشن کنید'
                        't3c2'
                        'پیامک'
                        'وارد کردن خودکار پیامک'
                        't3c1'
                        [Code]
                            File Name: jetvam.pyw
                            Object Name: changeDnsVal
                            Qualified Name: MyApp.showSettings.<locals>.changeDnsVal
                            Arg Count: 1
                            Pos Only Arg Count: 0
                            KW Only Arg Count: 0
                            Stack Size: 1
                            Flags: 0x00000013 (CO_OPTIMIZED | CO_NEWLOCALS | CO_NESTED)
                            [Names]
                                'dns_val'
                            [Locals+Names]
                                'number'
                            [Constants]
                                None
                            [Disassembly]
                                0       RESUME                          0
                                2       LOAD_FAST                       0: number
                                4       STORE_GLOBAL                    0: dns_val
                                6       LOAD_CONST                      0: None
                                8       RETURN_VALUE                    
                        'سرویس اتصال امن'
                        'نوع سرویس'
                        'خاموش'
                        [Code]
                            File Name: jetvam.pyw
                            Object Name: <lambda>
                            Qualified Name: MyApp.showSettings.<locals>.<lambda>
                            Arg Count: 0
                            Pos Only Arg Count: 0
                            KW Only Arg Count: 0
                            Stack Size: 3
                            Flags: 0x00000013 (CO_OPTIMIZED | CO_NEWLOCALS | CO_NESTED)
                            [Names]
                            [Locals+Names]
                                'changeDnsVal'
                            [Constants]
                                None
                                0
                            [Disassembly]
                                0       COPY_FREE_VARS                  1
                                2       RESUME                          0
                                4       PUSH_NULL                       
                                6       LOAD_DEREF                      0: changeDnsVal
                                8       LOAD_CONST                      1: 0
                                10      PRECALL                         1
                                14      CALL                            1
                                24      RETURN_VALUE                    
                        (
                            'text'
                            'value'
                            'variable'
                            'command'
                        )
                        'سرویس یک'
                        [Code]
                            File Name: jetvam.pyw
                            Object Name: <lambda>
                            Qualified Name: MyApp.showSettings.<locals>.<lambda>
                            Arg Count: 0
                            Pos Only Arg Count: 0
                            KW Only Arg Count: 0
                            Stack Size: 3
                            Flags: 0x00000013 (CO_OPTIMIZED | CO_NEWLOCALS | CO_NESTED)
                            [Names]
                            [Locals+Names]
                                'changeDnsVal'
                            [Constants]
                                None
                                1
                            [Disassembly]
                                0       COPY_FREE_VARS                  1
                                2       RESUME                          0
                                4       PUSH_NULL                       
                                6       LOAD_DEREF                      0: changeDnsVal
                                8       LOAD_CONST                      1: 1
                                10      PRECALL                         1
                                14      CALL                            1
                                24      RETURN_VALUE                    
                        'سرویس دو'
                        [Code]
                            File Name: jetvam.pyw
                            Object Name: <lambda>
                            Qualified Name: MyApp.showSettings.<locals>.<lambda>
                            Arg Count: 0
                            Pos Only Arg Count: 0
                            KW Only Arg Count: 0
                            Stack Size: 3
                            Flags: 0x00000013 (CO_OPTIMIZED | CO_NEWLOCALS | CO_NESTED)
                            [Names]
                            [Locals+Names]
                                'changeDnsVal'
                            [Constants]
                                None
                                2
                            [Disassembly]
                                0       COPY_FREE_VARS                  1
                                2       RESUME                          0
                                4       PUSH_NULL                       
                                6       LOAD_DEREF                      0: changeDnsVal
                                8       LOAD_CONST                      1: 2
                                10      PRECALL                         1
                                14      CALL                            1
                                24      RETURN_VALUE                    
                        'سرویس سه'
                        [Code]
                            File Name: jetvam.pyw
                            Object Name: <lambda>
                            Qualified Name: MyApp.showSettings.<locals>.<lambda>
                            Arg Count: 0
                            Pos Only Arg Count: 0
                            KW Only Arg Count: 0
                            Stack Size: 3
                            Flags: 0x00000013 (CO_OPTIMIZED | CO_NEWLOCALS | CO_NESTED)
                            [Names]
                            [Locals+Names]
                                'changeDnsVal'
                            [Constants]
                                None
                                3
                            [Disassembly]
                                0       COPY_FREE_VARS                  1
                                2       RESUME                          0
                                4       PUSH_NULL                       
                                6       LOAD_DEREF                      0: changeDnsVal
                                8       LOAD_CONST                      1: 3
                                10      PRECALL                         1
                                14      CALL                            1
                                24      RETURN_VALUE                    
                        (
                            'row'
                            'column'
                            'padx'
                        )
                        (
                            'row'
                            'column'
                        )
                        't4r1'
                        [Code]
                            File Name: jetvam.pyw
                            Object Name: <listcomp>
                            Qualified Name: MyApp.showSettings.<locals>.<listcomp>
                            Arg Count: 1
                            Pos Only Arg Count: 0
                            KW Only Arg Count: 0
                            Stack Size: 4
                            Flags: 0x00000013 (CO_OPTIMIZED | CO_NEWLOCALS | CO_NESTED)
                            [Names]
                                'state'
                            [Locals+Names]
                                '.0'
                                'i'
                            [Constants]
                            [Disassembly]
                                0       RESUME                          0
                                2       BUILD_LIST                      0
                                4       LOAD_FAST                       0: .0
                                6       FOR_ITER                        22 (to 52)
                                8       STORE_FAST                      1: i
                                10      LOAD_FAST                       1: i
                                12      LOAD_METHOD                     0: state
                                34      PRECALL                         0
                                38      CALL                            0
                                48      LIST_APPEND                     2
                                50      JUMP_BACKWARD                   23 (to 6)
                                52      RETURN_VALUE                    
                        [Code]
                            File Name: jetvam.pyw
                            Object Name: disableChildren
                            Qualified Name: MyApp.showSettings.<locals>.disableChildren
                            Arg Count: 1
                            Pos Only Arg Count: 0
                            KW Only Arg Count: 0
                            Stack Size: 4
                            Flags: 0x00000013 (CO_OPTIMIZED | CO_NEWLOCALS | CO_NESTED)
                            [Names]
                                'winfo_children'
                                'winfo_class'
                                'configure'
                            [Locals+Names]
                                'parent'
                                'child'
                                'wtype'
                                'disableChildren'
                            [Constants]
                                None
                                (
                                    'Frame'
                                    'Labelframe'
                                    'TFrame'
                                    'TLabelframe'
                                    'Canvas'
